{"roots":["15:1232"],"nodeById":{"1:3":{"id":"1:3","type":"VARIABLE","assetId":"VariableID:8033d4f0114a6e3fe444b55321be870ebb679842/18:2","name":"ButtonBgColor","resolvedType":"COLOR","valuesByMode":{"18:0":{"r":0.0,"g":0.0,"b":0.0,"a":1.0}},"variableCollectionId":"VariableCollectionId:7c5f5a79620c1c68e6e553b7b51078dd6262a5d7/18:0","codeSyntax":{}},"50:2742":{"type":"TEXT","id":"50:2742","name":"A paper magazine could solve all these problems! Must an Instagram competitor be digital?","overrideKey":"74:736","absoluteBoundingBox":{"x":2719.0,"y":12791.0,"width":651.0,"height":410.0},"isolatedAbsoluteRenderBounds":{"x":2721.303955078125,"y":12809.16015625,"width":628.31201171875,"height":326.080078125},"relativeTransform":[[1.0,0.0,655.5],[0.0,1.0,699.9999389648438]],"size":{"x":651.0,"y":410.0},"fills":[{"blendMode":"NORMAL","type":"SOLID","color":{"r":0.0,"g":0.0,"b":0.0,"a":1.0},"visible":true,"opacity":1.0}],"constraintValues":{"left":{"pixelOffset":655.5,"sizeFraction":0.0},"top":{"pixelOffset":699.9999389648438,"sizeFraction":0.0}},"strokeAlign":"OUTSIDE","strokes":[],"effects":[],"accessibleHTMLTag":"AUTO","isDecorativeImage":false,"ariaAttributes":{},"interactions":[],"characterStyleOverrides":[17,17,16,16,16,16,16,16,16,16,16,16,16,16,16,16,17,17,17,17,17,17,17,17,17,17,17,17,17,17,17,17,17,17,17,17,17,17,17,17,17,17,17,17,17,17,17,17,17,17,17,17,17,17,17,17,17,17,17,17,17,17,17,17,17,17,17,17,17,17,17,17,17,17,17,17,17,17,17,17,17,17,17,17,17,17,17,17,17,17,17],"characters":"A paper magazine could solve all these problems!\n\nMust an Instagram competitor be digital?\n","lineIndentations":[0,0,0,0],"lineTypes":["NONE","NONE","NONE","NONE"],"listStartOffsets":[],"lineStyleOverrides":[0,0,0,0],"lineTextDirections":null,"style":{"fontFamily":"VT323","fontPostScriptName":"VT323-Regular","fontStyle":"Regular","fontVariantPosition":"NORMAL","fontSize":64.0,"textAlignHorizontal":"LEFT","textAlignVertical":"TOP","letterSpacing":0.0,"letterSpacingValue":0.0,"letterSpacingUnit":"PERCENT","lineHeightPx":70.0,"lineHeightPercent":109.375,"lineHeightPercentFontSize":109.375,"lineHeightUnit":"PIXELS","paragraphSpacing":0,"paragraphIndent":0,"listSpacing":0,"italic":false,"textCase":"ORIGINAL","textDecoration":"NONE","textDecorationSkipInk":false,"textDecorationStyle":"solid","textAutoResize":"NONE","textTruncation":"DISABLED"},"styleOverrideTable":{"17":{"fontSize":64.0,"paragraphSpacing":0,"paragraphIndent":0,"listSpacing":0,"italic":false,"textCase":"ORIGINAL","textDecoration":"NONE","textDecorationSkipInk":false,"textDecorationStyle":"solid","textAutoResize":"NONE","textTruncation":"DISABLED","lineHeightPercent":100,"lineHeightPercentFontSize":100},"16":{"fontSize":64.0,"fills":[{"blendMode":"NORMAL","type":"SOLID","color":{"r":0.07450980693101883,"g":0.20000000298023224,"b":0.800000011920929,"a":1.0},"visible":true,"opacity":1.0}],"lineHeightPx":70.0,"lineHeightPercent":93.33333587646484,"lineHeightPercentFontSize":109.375,"lineHeightUnit":"PIXELS","paragraphSpacing":0,"paragraphIndent":0,"listSpacing":0,"italic":false,"textCase":"ORIGINAL","textDecoration":"NONE","textDecorationSkipInk":false,"textDecorationStyle":"solid","textAutoResize":"NONE","textTruncation":"DISABLED"}}},"50:2700":{"type":"FRAME","id":"50:2700","name":"Frame 45","overrideKey":"74:695","absoluteBoundingBox":{"x":1998.0,"y":10548.0,"width":1632.0,"height":716.0},"isolatedAbsoluteRenderBounds":{"x":1998.0,"y":10422.0,"width":1632.0,"height":971.0},"relativeTransform":[[1.0,0.0,-12.0],[0.0,1.0,1631.0]],"size":{"x":1632.0,"y":716.0},"fills":[],"constraintValues":{"left":{"pixelOffset":-12.0,"sizeFraction":0.0},"top":{"pixelOffset":1631.0,"sizeFraction":0.0}},"strokeAlign":"INSIDE","strokes":[],"effects":[],"accessibleHTMLTag":"AUTO","isDecorativeImage":false,"ariaAttributes":{},"interactions":[],"children":["50:2701"]},"50:2701":{"type":"FRAME","id":"50:2701","name":"Frame 46","overrideKey":"99:360","absoluteBoundingBox":{"x":1998.0,"y":10422.0,"width":1632.0,"height":971.0},"isolatedAbsoluteRenderBounds":{"x":1998.0,"y":10422.0,"width":1632.0,"height":971.0},"relativeTransform":[[1.0,0.0,0.0],[0.0,1.0,-126.0]],"size":{"x":1632.0,"y":971.0},"fills":[],"constraintValues":{"left":{"pixelOffset":0.0,"sizeFraction":0.0},"top":{"pixelOffset":-126.0,"sizeFraction":0.0}},"strokeAlign":"INSIDE","strokes":[],"effects":[],"accessibleHTMLTag":"AUTO","isDecorativeImage":false,"ariaAttributes":{},"interactions":[],"children":["50:2702","50:2703","50:2704","50:2705"]},"50:2704":{"type":"TEXT","id":"50:2704","name":"A paper magazine for stationery lovers","overrideKey":"99:363","absoluteBoundingBox":{"x":2930.0,"y":10687.0,"width":367.0,"height":299.0},"isolatedAbsoluteRenderBounds":{"x":2930.47998046875,"y":10697.8798828125,"width":317.840087890625,"height":127.560546875},"relativeTransform":[[1.0,0.0,932.0],[0.0,1.0,265.0]],"size":{"x":367.0,"y":299.0},"fills":[{"blendMode":"NORMAL","type":"SOLID","color":{"r":0.0,"g":0.0,"b":0.0,"a":1.0},"visible":true,"opacity":1.0}],"constraintValues":{"left":{"pixelOffset":932.0,"sizeFraction":0.0},"top":{"pixelOffset":265.0,"sizeFraction":0.0}},"strokeAlign":"OUTSIDE","strokes":[],"effects":[],"accessibleHTMLTag":"AUTO","isDecorativeImage":false,"ariaAttributes":{},"interactions":[],"characterStyleOverrides":[75,75,74,74,74,74,74,74,74,74,74,74,74,74,74,74,75,75,75,75,75,75,75,75,75,75,75,75,75,75,75,75,75,75,75,75,75,75],"characters":"A paper magazine for stationery lovers","lineIndentations":[0],"lineTypes":["NONE"],"listStartOffsets":[],"lineStyleOverrides":[0],"lineTextDirections":null,"style":{"fontFamily":"Inconsolata","fontPostScriptName":"Inconsolata-Regular","fontStyle":"Regular","fontVariantPosition":"NORMAL","fontSize":40.0,"textAlignHorizontal":"LEFT","textAlignVertical":"TOP","letterSpacing":0.0,"letterSpacingValue":0.0,"letterSpacingUnit":"PERCENT","lineHeightPx":50.0,"lineHeightPercent":119.16110229492188,"lineHeightPercentFontSize":125.0,"lineHeightUnit":"PIXELS","paragraphSpacing":0,"paragraphIndent":0,"listSpacing":0,"italic":false,"textCase":"ORIGINAL","textDecoration":"NONE","textDecorationSkipInk":false,"textDecorationStyle":"solid","textAutoResize":"NONE","textTruncation":"DISABLED"},"styleOverrideTable":{"75":{"fontFamily":"Inconsolata","fontPostScriptName":"Inconsolata-Bold","fontStyle":"Bold","fontSize":40.0,"lineHeightPx":50.0,"lineHeightPercent":119.16110229492188,"lineHeightPercentFontSize":125.0,"lineHeightUnit":"PIXELS","paragraphSpacing":0,"paragraphIndent":0,"listSpacing":0,"italic":false,"textCase":"ORIGINAL","textDecoration":"NONE","textDecorationSkipInk":false,"textDecorationStyle":"solid","textAutoResize":"NONE","textTruncation":"DISABLED"},"74":{"fontFamily":"Inconsolata","fontPostScriptName":"Inconsolata-Bold","fontStyle":"Bold","fontSize":40.0,"fills":[{"blendMode":"NORMAL","type":"SOLID","color":{"r":0.07450980693101883,"g":0.20000000298023224,"b":0.800000011920929,"a":1.0},"visible":true,"opacity":1.0}],"lineHeightPx":50.0,"lineHeightPercent":119.16110229492188,"lineHeightPercentFontSize":125.0,"lineHeightUnit":"PIXELS","paragraphSpacing":0,"paragraphIndent":0,"listSpacing":0,"italic":false,"textCase":"ORIGINAL","textDecoration":"NONE","textDecorationSkipInk":false,"textDecorationStyle":"solid","textAutoResize":"NONE","textTruncation":"DISABLED"}}},"50:2703":{"type":"RECTANGLE","id":"50:2703","name":"image 48","overrideKey":"99:362","absoluteBoundingBox":{"x":2577.0,"y":10541.0,"width":791.0,"height":432.0},"targetAspectRatio":{"x":2048.0,"y":1117.0},"isolatedAbsoluteRenderBounds":{"x":2577.0,"y":10541.0,"width":791.0,"height":432.0},"relativeTransform":[[1.0,0.0,579.0],[0.0,1.0,119.0]],"size":{"x":791.0,"y":432.0},"fills":[{"blendMode":"NORMAL","type":"IMAGE","scaleMode":"FILL","imageRef":"40161369bf6fe385afffb3f01db62d408e0698a2","originalImageWidth":2048,"originalImageHeight":1117,"visible":true,"opacity":1.0,"rotation":0.0}],"constraintValues":{"left":{"pixelOffset":579.0,"sizeFraction":0.0},"top":{"pixelOffset":119.0,"sizeFraction":0.0}},"strokeAlign":"INSIDE","strokes":[],"effects":[],"accessibleHTMLTag":"AUTO","isDecorativeImage":false,"ariaAttributes":{},"interactions":[]},"50:2699":{"type":"TEXT","id":"50:2699","name":"and by that I meant:","overrideKey":"74:696","absoluteBoundingBox":{"x":2026.0,"y":10022.0,"width":1600.0,"height":142.0},"isolatedAbsoluteRenderBounds":{"x":2587.925537109375,"y":10066.400390625,"width":469.525390625,"height":43.19921875},"relativeTransform":[[1.0,0.0,16.0],[0.0,1.0,1105.0]],"size":{"x":1600.0,"y":142.0},"fills":[{"blendMode":"NORMAL","type":"SOLID","color":{"r":0.0,"g":0.0,"b":0.0,"a":1.0},"visible":true,"opacity":1.0}],"constraints":{"vertical":"TOP","horizontal":"CENTER"},"constraintValues":{"left":{"pixelOffset":-800.0,"sizeFraction":0.5},"right":{"pixelOffset":800.0,"sizeFraction":0.5},"top":{"pixelOffset":1105.0,"sizeFraction":0.0}},"strokeAlign":"OUTSIDE","strokes":[],"effects":[],"accessibleHTMLTag":"AUTO","isDecorativeImage":false,"ariaAttributes":{},"interactions":[],"characterStyleOverrides":[],"characters":"and by that I meant:\n","lineIndentations":[0,0],"lineTypes":["NONE","NONE"],"listStartOffsets":[],"lineStyleOverrides":[0,0],"lineTextDirections":null,"textAlignHorizontal":"CENTER","style":{"fontFamily":"VT323","fontPostScriptName":"VT323-Regular","fontStyle":"Regular","fontVariantPosition":"NORMAL","fontSize":60.0,"textAlignHorizontal":"CENTER","textAlignVertical":"TOP","letterSpacing":0.0,"letterSpacingValue":0.0,"letterSpacingUnit":"PERCENT","lineHeightPx":120.0,"lineHeightPercent":200.0,"lineHeightPercentFontSize":200.0,"lineHeightUnit":"PIXELS","paragraphSpacing":0,"paragraphIndent":0,"listSpacing":0,"italic":false,"textCase":"ORIGINAL","textDecoration":"NONE","textDecorationSkipInk":false,"textDecorationStyle":"solid","textAutoResize":"NONE","textTruncation":"DISABLED"},"styleOverrideTable":{}},"50:2694":{"type":"FRAME","id":"50:2694","name":"Frame 44","overrideKey":"74:694","absoluteBoundingBox":{"x":2010.0,"y":8917.0,"width":1632.0,"height":971.0},"isolatedAbsoluteRenderBounds":{"x":2010.0,"y":8917.0,"width":1632.0,"height":971.0},"relativeTransform":[[1.0,0.0,0.0],[0.0,1.0,0.0]],"size":{"x":1632.0,"y":971.0},"fills":[],"constraintValues":{"left":{"pixelOffset":0.0,"sizeFraction":0.0},"top":{"pixelOffset":0.0,"sizeFraction":0.0}},"strokeAlign":"INSIDE","strokes":[],"effects":[],"accessibleHTMLTag":"AUTO","isDecorativeImage":false,"ariaAttributes":{},"interactions":[],"children":["50:2695","50:2696","50:2697","50:2698"]},"50:2698":{"type":"TEXT","id":"50:2698","name":"I should make an\u2028Instagram alternative for journalers","overrideKey":"74:692","absoluteBoundingBox":{"x":2771.0,"y":9137.0,"width":634.0,"height":266.0},"isolatedAbsoluteRenderBounds":{"x":2772.7099609375,"y":9157.0751953125,"width":468.900146484375,"height":177.8447265625},"relativeTransform":[[1.0,0.0,761.0],[0.0,1.0,220.0]],"size":{"x":634.0,"y":266.0},"fills":[{"blendMode":"NORMAL","type":"SOLID","color":{"r":0.0,"g":0.0,"b":0.0,"a":1.0},"visible":true,"opacity":1.0}],"constraintValues":{"left":{"pixelOffset":761.0,"sizeFraction":0.0},"top":{"pixelOffset":220.0,"sizeFraction":0.0}},"strokeAlign":"OUTSIDE","strokes":[],"effects":[],"accessibleHTMLTag":"AUTO","isDecorativeImage":false,"ariaAttributes":{},"interactions":[],"characterStyleOverrides":[56,56,56,56,56,56,56,56,56,56,56,56,56,56,56,56,56,55,55,55,55,55,55,55,55,55,55,55,55,55,55,55,55,55,55,55,55,55,55,55,55,55,55,55,55,55,55,55,55,55,55,55,55,55,55],"characters":"I should make an\u2028Instagram alternative\nfor journalers\n\n","lineIndentations":[0,0,0,0],"lineTypes":["NONE","NONE","NONE","NONE"],"listStartOffsets":[],"lineStyleOverrides":[0,0,0,0],"lineTextDirections":null,"style":{"fontFamily":"Inclusive Sans","fontPostScriptName":"InclusiveSans-Regular","fontStyle":"Regular","fontVariantPosition":"NORMAL","fontSize":45.0,"textAlignHorizontal":"LEFT","textAlignVertical":"TOP","letterSpacing":0.0,"letterSpacingValue":0.0,"letterSpacingUnit":"PERCENT","lineHeightPx":70.0,"lineHeightPercent":129.62962341308594,"lineHeightPercentFontSize":155.55555725097656,"lineHeightUnit":"PIXELS","paragraphSpacing":0,"paragraphIndent":0,"listSpacing":0,"italic":false,"textCase":"ORIGINAL","textDecoration":"NONE","textDecorationSkipInk":false,"textDecorationStyle":"solid","textAutoResize":"NONE","textTruncation":"DISABLED"},"styleOverrideTable":{"56":{"fontFamily":"Inconsolata","fontPostScriptName":"Inconsolata-Regular","fontStyle":"Regular","fontSize":45.0,"lineHeightPx":70.0,"lineHeightPercent":148.28936767578125,"lineHeightPercentFontSize":155.55555725097656,"lineHeightUnit":"PIXELS","paragraphSpacing":0,"paragraphIndent":0,"listSpacing":0,"italic":false,"textCase":"ORIGINAL","textDecoration":"NONE","textDecorationSkipInk":false,"textDecorationStyle":"solid","textAutoResize":"NONE","textTruncation":"DISABLED"},"55":{"fontFamily":"Inconsolata","fontPostScriptName":"Inconsolata-Bold","fontStyle":"Bold","fontSize":45.0,"lineHeightPx":70.0,"lineHeightPercent":148.28936767578125,"lineHeightPercentFontSize":155.55555725097656,"lineHeightUnit":"PIXELS","paragraphSpacing":0,"paragraphIndent":0,"listSpacing":0,"italic":false,"textCase":"ORIGINAL","textDecoration":"NONE","textDecorationSkipInk":false,"textDecorationStyle":"solid","textAutoResize":"NONE","textTruncation":"DISABLED"}}},"50:2659":{"type":"RECTANGLE","id":"50:2659","name":"image 39","overrideKey":"74:647","absoluteBoundingBox":{"x":2926.0,"y":408.0,"width":559.0,"height":517.0},"targetAspectRatio":{"x":1024.0,"y":947.0},"isolatedAbsoluteRenderBounds":{"x":2926.0,"y":408.0,"width":559.0,"height":517.0},"relativeTransform":[[1.0,0.0,900.0],[0.0,1.0,80.0]],"size":{"x":559.0,"y":517.0},"fills":[{"blendMode":"NORMAL","type":"IMAGE","scaleMode":"FILL","imageRef":"e788d7b73a8a70c534a3c5cbc04bd076221ee7d2","originalImageWidth":1024,"originalImageHeight":947,"visible":true,"opacity":1.0,"rotation":0.0}],"constraintValues":{"left":{"pixelOffset":900.0,"sizeFraction":0.0},"top":{"pixelOffset":80.0,"sizeFraction":0.0}},"strokeAlign":"INSIDE","strokes":[],"effects":[],"accessibleHTMLTag":"AUTO","isDecorativeImage":false,"ariaAttributes":{},"interactions":[]},"50:2696":{"type":"RECTANGLE","id":"50:2696","name":"image 47","overrideKey":"74:690","absoluteBoundingBox":{"x":2159.0,"y":9233.0,"width":439.0,"height":453.0},"targetAspectRatio":{"x":858.0,"y":886.0},"isolatedAbsoluteRenderBounds":{"x":2159.0,"y":9233.0,"width":439.0,"height":453.0},"relativeTransform":[[1.0,0.0,149.0],[0.0,1.0,316.0]],"size":{"x":439.0,"y":453.0},"fills":[{"blendMode":"NORMAL","type":"IMAGE","scaleMode":"FILL","imageRef":"ab920b0f26621e113e5411c1bbf88b324f20cc48","originalImageWidth":858,"originalImageHeight":886,"visible":true,"opacity":1.0,"rotation":0.0}],"constraintValues":{"left":{"pixelOffset":149.0,"sizeFraction":0.0},"top":{"pixelOffset":316.0,"sizeFraction":0.0}},"strokeAlign":"INSIDE","strokes":[],"effects":[],"accessibleHTMLTag":"AUTO","isDecorativeImage":false,"ariaAttributes":{},"interactions":[]},"50:2670":{"type":"FRAME","id":"50:2670","name":"Frame 72","overrideKey":"99:192","absoluteBoundingBox":{"x":2179.0,"y":6551.0,"width":1294.0,"height":1466.0},"isolatedAbsoluteRenderBounds":{"x":2160.468017578125,"y":6551.0,"width":1315.224609375,"height":1466.0},"relativeTransform":[[1.0,0.0,153.0],[0.0,1.0,7816.0]],"size":{"x":1294.0,"y":1466.0},"fills":[],"strokeAlign":"INSIDE","strokes":[],"effects":[],"accessibleHTMLTag":"AUTO","isDecorativeImage":false,"ariaAttributes":{},"interactions":[],"children":["50:2671","50:2672","50:2673","50:2683"]},"50:2683":{"type":"GROUP","id":"50:2683","name":"Group 5","overrideKey":"99:316","absoluteBoundingBox":{"x":2540.0,"y":7218.00244140625,"width":944.2022705078125,"height":662.99755859375},"isolatedAbsoluteRenderBounds":{"x":2540.0,"y":7218.00244140625,"width":944.2022705078125,"height":662.99755859375},"relativeTransform":[[1.0,0.0,361.0],[0.0,1.0,667.00244140625]],"size":{"x":944.2022705078125,"y":662.99755859375},"fills":[],"constraints":{"vertical":"SCALE","horizontal":"SCALE"},"constraintValues":{"left":{"pixelOffset":-5.684341886080802e-14,"sizeFraction":0.2789799072642968},"right":{"pixelOffset":2.2737367544323206e-13,"sizeFraction":1.0086570869457592},"top":{"pixelOffset":0.0,"sizeFraction":0.4549812015049454},"bottom":{"pixelOffset":0.0,"sizeFraction":0.9072305593451568}},"strokeAlign":"INSIDE","strokes":[],"effects":[],"accessibleHTMLTag":"AUTO","isDecorativeImage":false,"ariaAttributes":{},"interactions":[],"children":["50:2684","50:2685","50:2692"]},"50:2652":{"type":"TEXT","id":"50:2652","name":"(Here are just a few of the US-based stationery conventions started in the last 12 months!)","overrideKey":"74:673","absoluteBoundingBox":{"x":2170.0,"y":2740.0,"width":1313.0,"height":139.0},"isolatedAbsoluteRenderBounds":{"x":2362.341064453125,"y":2758.0,"width":932.79833984375,"height":106.0},"relativeTransform":[[1.0,0.0,144.0],[0.0,1.0,2412.0]],"size":{"x":1313.0,"y":139.0},"fills":[{"blendMode":"NORMAL","type":"SOLID","color":{"r":0.11940062791109085,"g":0.5249211192131042,"b":0.5107749700546265,"a":1.0},"visible":true,"opacity":1.0}],"constraints":{"vertical":"TOP","horizontal":"CENTER"},"constraintValues":{"left":{"pixelOffset":-656.0,"sizeFraction":0.5},"right":{"pixelOffset":657.0,"sizeFraction":0.5},"top":{"pixelOffset":2412.0,"sizeFraction":0.0}},"strokeAlign":"OUTSIDE","strokes":[],"effects":[],"accessibleHTMLTag":"AUTO","isDecorativeImage":false,"ariaAttributes":{},"interactions":[],"characterStyleOverrides":[],"characters":"(Here are just a few of the US-based stationery\nconventions started in the last 12 months!)","lineIndentations":[0,0],"lineTypes":["NONE","NONE"],"listStartOffsets":[],"lineStyleOverrides":[0,0],"lineTextDirections":null,"textAlignHorizontal":"CENTER","style":{"fontFamily":"VT323","fontPostScriptName":"VT323-Regular","fontStyle":"Regular","fontVariantPosition":"NORMAL","fontSize":50.0,"textAlignHorizontal":"CENTER","textAlignVertical":"TOP","letterSpacing":0.0,"letterSpacingValue":0.0,"letterSpacingUnit":"PERCENT","lineHeightPx":70.0,"lineHeightPercent":140.0,"lineHeightPercentFontSize":140.0,"lineHeightUnit":"PIXELS","paragraphSpacing":0,"paragraphIndent":0,"listSpacing":0,"italic":false,"textCase":"ORIGINAL","textDecoration":"NONE","textDecorationSkipInk":false,"textDecorationStyle":"solid","textAutoResize":"NONE","textTruncation":"DISABLED"},"styleOverrideTable":{}},"50:2685":{"type":"SVG","id":"50:2685","name":"Group 7","overrideKey":"99:318","absoluteBoundingBox":{"x":2540.0,"y":7218.00244140625,"width":944.2022705078125,"height":662.99755859375},"isolatedAbsoluteRenderBounds":{"x":2540.0,"y":7218.00244140625,"width":944.2022705078125,"height":662.99755859375},"relativeTransform":[[1.0,0.0,-4.547473508864641e-13],[0.0,1.0,0.0]],"size":{"x":944.2022705078125,"y":662.99755859375},"fills":[],"constraints":{"vertical":"SCALE","horizontal":"SCALE"},"constraintValues":{"left":{"pixelOffset":0.0,"sizeFraction":0.2789799072642964},"right":{"pixelOffset":0.0,"sizeFraction":1.008657086945759},"top":{"pixelOffset":0.0,"sizeFraction":0.4549812015049454},"bottom":{"pixelOffset":0.0,"sizeFraction":0.9072305593451568}},"strokeAlign":"INSIDE","strokes":[],"accessibleHTMLTag":"AUTO","isDecorativeImage":false,"ariaAttributes":{},"interactions":[],"hash":"98597c0a5a579be0a09b2d425ff52185b699971f"},"50:2673":{"type":"GROUP","id":"50:2673","name":"Group 6","overrideKey":"99:292","absoluteBoundingBox":{"x":2747.0,"y":6603.0,"width":704.1134033203125,"height":645.1104736328125},"isolatedAbsoluteRenderBounds":{"x":2747.0,"y":6603.0,"width":704.113525390625,"height":645.1104736328125},"relativeTransform":[[1.0,0.0,568.0],[0.0,1.0,52.0]],"size":{"x":704.1134033203125,"y":645.1104736328125},"fills":[],"constraints":{"vertical":"TOP","horizontal":"LEFT"},"constraintValues":{"left":{"pixelOffset":568.0,"sizeFraction":0.0},"top":{"pixelOffset":52.0,"sizeFraction":0.0}},"strokeAlign":"INSIDE","strokes":[],"effects":[],"accessibleHTMLTag":"AUTO","isDecorativeImage":false,"ariaAttributes":{},"interactions":[],"children":["50:2674"]},"50:2682":{"type":"TEXT","id":"50:2682","name":"What we gain from Instagram: 💖 Sense of community 💖 A way to stay connected 💖 Journaling \u0026 stationery news, products, ideas, inspiration 💖 Engaging visual content","overrideKey":"99:312","absoluteBoundingBox":{"x":2786.0,"y":6647.18212890625,"width":656.0,"height":413.0},"isolatedAbsoluteRenderBounds":{"x":2786.0,"y":6669.7421875,"width":630.401123046875,"height":385.27978515625},"relativeTransform":[[1.0,0.0,39.0],[0.0,1.0,44.18231201171875]],"size":{"x":656.0,"y":413.0},"fills":[{"blendMode":"NORMAL","type":"SOLID","color":{"r":0.0,"g":0.0,"b":0.0,"a":1.0},"visible":true,"opacity":1.0}],"constraints":{"vertical":"SCALE","horizontal":"SCALE"},"constraintValues":{"left":{"pixelOffset":0.0,"sizeFraction":0.05538880500796017},"right":{"pixelOffset":0.0,"sizeFraction":0.9870569097572388},"top":{"pixelOffset":0.0,"sizeFraction":0.06848797813328741},"bottom":{"pixelOffset":0.0,"sizeFraction":0.708688404076261}},"strokeAlign":"OUTSIDE","strokes":[],"effects":[],"accessibleHTMLTag":"AUTO","isDecorativeImage":false,"ariaAttributes":{},"interactions":[],"characterStyleOverrides":[0,0,0,1,1,1,1,1,1,1,1,1,1,1,1,1,1,1,1,1,1,1,1,1,1,1,1,1,1,1,1,1],"characters":"   What we gain from Instagram:\n💖 Sense of community\n💖 A way to stay connected\n💖 Journaling \u0026 stationery news,\n   products, ideas, inspiration\n💖 Engaging visual content\n","lineIndentations":[0,0,0,0,0,0,0],"lineTypes":["NONE","NONE","NONE","NONE","NONE","NONE","NONE"],"listStartOffsets":[],"lineStyleOverrides":[0,0,0,0,0,0,0],"lineTextDirections":null,"fallbackFonts":[{"fontFamily":"Noto Sans","fontStyle":"Regular"}],"style":{"fontFamily":"VT323","fontPostScriptName":"VT323-Regular","fontStyle":"Regular","fallbackFonts":[{"fontFamily":"Noto Sans","fontStyle":"Regular"}],"fontVariantPosition":"NORMAL","fontSize":49.0,"textAlignHorizontal":"LEFT","textAlignVertical":"TOP","letterSpacing":0.0,"letterSpacingValue":0.0,"letterSpacingUnit":"PERCENT","lineHeightPx":70.0,"lineHeightPercent":142.85714721679688,"lineHeightPercentFontSize":142.85714721679688,"lineHeightUnit":"PIXELS","paragraphSpacing":0,"paragraphIndent":0,"listSpacing":0,"italic":false,"textCase":"ORIGINAL","textDecoration":"NONE","textDecorationSkipInk":false,"textDecorationStyle":"solid","textAutoResize":"NONE","textTruncation":"DISABLED"},"styleOverrideTable":{"1":{"fallbackFonts":[{"fontFamily":"Noto Sans","fontStyle":"Regular"}],"textDecoration":"UNDERLINE","paragraphSpacing":0,"paragraphIndent":0,"listSpacing":0,"italic":false,"textCase":"ORIGINAL","textDecorationSkipInk":false,"textDecorationStyle":"solid","textAutoResize":"NONE","textTruncation":"DISABLED","lineHeightPercent":100,"lineHeightPercentFontSize":100}}},"50:2676":{"type":"SVG","id":"50:2676","name":"Group 8","overrideKey":"99:295","absoluteBoundingBox":{"x":2747.0,"y":6603.0,"width":704.1134033203125,"height":507.28033447265625},"isolatedAbsoluteRenderBounds":{"x":2747.0,"y":6603.0,"width":704.113525390625,"height":507.28033447265625},"relativeTransform":[[1.0,0.0,0.0],[0.0,1.0,0.0]],"size":{"x":704.1134033203125,"y":507.28033447265625},"fills":[],"constraints":{"vertical":"SCALE","horizontal":"SCALE"},"constraintValues":{"left":{"pixelOffset":0.0,"sizeFraction":0.0},"right":{"pixelOffset":0.0,"sizeFraction":1.0},"top":{"pixelOffset":0.0,"sizeFraction":0.0},"bottom":{"pixelOffset":-5.684341886080802e-14,"sizeFraction":0.7863464556946457}},"strokeAlign":"INSIDE","strokes":[],"accessibleHTMLTag":"AUTO","isDecorativeImage":false,"ariaAttributes":{},"interactions":[],"hash":"c50563e3e046bfa0b1fa6545757236cc447d9f3a"},"50:2672":{"type":"TEXT","id":"50:2672","name":"Generally speaking, this is why the analog community is on Instagram:","overrideKey":"99:314","absoluteBoundingBox":{"x":2217.0,"y":6717.0,"width":436.0,"height":240.0},"isolatedAbsoluteRenderBounds":{"x":2274.428955078125,"y":6734.0,"width":376.75146484375,"height":216.0},"relativeTransform":[[1.0,0.0,38.0],[0.0,1.0,166.0]],"size":{"x":436.0,"y":240.0},"fills":[{"blendMode":"NORMAL","type":"SOLID","color":{"r":0.0,"g":0.0,"b":0.0,"a":1.0},"visible":true,"opacity":1.0}],"constraintValues":{"left":{"pixelOffset":38.0,"sizeFraction":0.0},"top":{"pixelOffset":166.0,"sizeFraction":0.0}},"strokeAlign":"OUTSIDE","strokes":[],"effects":[],"accessibleHTMLTag":"AUTO","isDecorativeImage":false,"ariaAttributes":{},"interactions":[],"characterStyleOverrides":[],"characters":"Generally speaking, this is why the analog community is on Instagram:","lineIndentations":[0],"lineTypes":["NONE"],"listStartOffsets":[],"lineStyleOverrides":[0],"lineTextDirections":null,"textAlignHorizontal":"RIGHT","style":{"fontFamily":"VT323","fontPostScriptName":"VT323-Regular","fontStyle":"Regular","fontVariantPosition":"NORMAL","fontSize":50.0,"textAlignHorizontal":"RIGHT","textAlignVertical":"TOP","letterSpacing":0.0,"letterSpacingValue":0.0,"letterSpacingUnit":"PERCENT","lineHeightPx":60.0,"lineHeightPercent":120.00000762939453,"lineHeightPercentFontSize":120.0,"lineHeightUnit":"PIXELS","paragraphSpacing":0,"paragraphIndent":0,"listSpacing":0,"italic":false,"textCase":"ORIGINAL","textDecoration":"NONE","textDecorationSkipInk":false,"textDecorationStyle":"solid","textAutoResize":"NONE","textTruncation":"DISABLED"},"styleOverrideTable":{}},"50:2663":{"type":"FRAME","id":"50:2663","name":"Frame 71","overrideKey":"93:177","absoluteBoundingBox":{"x":2179.0,"y":4859.0,"width":1294.0,"height":792.0},"isolatedAbsoluteRenderBounds":{"x":2176.0,"y":4859.0,"width":1341.0,"height":792.0},"relativeTransform":[[1.0,0.0,153.0],[0.0,1.0,6124.0]],"size":{"x":1294.0,"y":792.0},"fills":[],"strokeAlign":"INSIDE","strokes":[],"effects":[],"accessibleHTMLTag":"AUTO","isDecorativeImage":false,"ariaAttributes":{},"interactions":[],"children":["50:2664","50:2665","50:2666","50:2667","50:2668","50:2669"]},"50:2668":{"type":"RECTANGLE","id":"50:2668","name":"CleanShot 2025-09-28 at 11.50.29@2x 1","overrideKey":"93:184","absoluteBoundingBox":{"x":3080.0,"y":4929.0,"width":437.0,"height":267.0},"targetAspectRatio":{"x":3000.0,"y":1830.0},"isolatedAbsoluteRenderBounds":{"x":3080.0,"y":4929.0,"width":437.0,"height":267.0},"relativeTransform":[[1.0,0.0,901.0],[0.0,1.0,70.0]],"size":{"x":437.0,"y":267.0},"fills":[{"blendMode":"NORMAL","type":"IMAGE","scaleMode":"FILL","imageRef":"ef2ddfc80b0b1b6ed8ad976d16042510832e806c","originalImageWidth":3000,"originalImageHeight":1830,"visible":true,"opacity":1.0,"rotation":0.0}],"constraintValues":{"left":{"pixelOffset":901.0,"sizeFraction":0.0},"top":{"pixelOffset":70.0,"sizeFraction":0.0}},"strokeAlign":"INSIDE","strokes":[],"effects":[],"accessibleHTMLTag":"AUTO","isDecorativeImage":false,"ariaAttributes":{},"interactions":[]},"50:2667":{"type":"RECTANGLE","id":"50:2667","name":"image 95","overrideKey":"93:179","absoluteBoundingBox":{"x":2176.0,"y":4929.0,"width":389.0,"height":240.0},"targetAspectRatio":{"x":1200.0,"y":738.0},"isolatedAbsoluteRenderBounds":{"x":2176.0,"y":4929.0,"width":389.0,"height":240.0},"relativeTransform":[[1.0,0.0,-3.0],[0.0,1.0,70.0]],"size":{"x":389.0,"y":240.0},"fills":[{"blendMode":"NORMAL","type":"IMAGE","scaleMode":"FILL","imageRef":"1a28191bd5e037e02ee2cf096fb0a7ebc269581a","originalImageWidth":1200,"originalImageHeight":738,"visible":true,"opacity":1.0,"rotation":0.0}],"constraintValues":{"left":{"pixelOffset":-3.0,"sizeFraction":0.0},"top":{"pixelOffset":70.0,"sizeFraction":0.0}},"strokeAlign":"INSIDE","strokes":[],"effects":[],"accessibleHTMLTag":"AUTO","isDecorativeImage":false,"ariaAttributes":{},"interactions":[]},"50:2666":{"type":"RECTANGLE","id":"50:2666","name":"CleanShot 2025-09-28 at 11.54.25@2x 1","overrideKey":"99:187","absoluteBoundingBox":{"x":2875.0,"y":5244.0,"width":436.0,"height":232.0},"targetAspectRatio":{"x":2020.0,"y":1076.0},"isolatedAbsoluteRenderBounds":{"x":2875.0,"y":5244.0,"width":436.0,"height":232.0},"relativeTransform":[[1.0,0.0,696.0],[0.0,1.0,385.0]],"size":{"x":436.0,"y":232.0},"fills":[{"blendMode":"NORMAL","type":"IMAGE","scaleMode":"FILL","imageRef":"fdc67aafac07ebde7f933aece5dcbe07a53e38a6","originalImageWidth":2020,"originalImageHeight":1076,"visible":true,"opacity":1.0,"rotation":0.0}],"constraintValues":{"left":{"pixelOffset":696.0,"sizeFraction":0.0},"top":{"pixelOffset":385.0,"sizeFraction":0.0}},"strokeAlign":"INSIDE","strokes":[],"effects":[],"accessibleHTMLTag":"AUTO","isDecorativeImage":false,"ariaAttributes":{},"interactions":[]},"50:2665":{"type":"TEXT","id":"50:2665","name":"We’d all leave the platform if there was a realistic alternative for our community","overrideKey":"99:202","absoluteBoundingBox":{"x":2471.0,"y":5505.0,"width":828.0,"height":146.0},"isolatedAbsoluteRenderBounds":{"x":2479.999267578125,"y":5514.0,"width":817.18115234375,"height":104.0},"relativeTransform":[[1.0,0.0,292.0],[0.0,1.0,646.0]],"size":{"x":828.0,"y":146.0},"fills":[{"blendMode":"NORMAL","type":"SOLID","color":{"r":0.0,"g":0.0,"b":0.0,"a":1.0},"visible":true,"opacity":1.0}],"constraintValues":{"left":{"pixelOffset":292.0,"sizeFraction":0.0},"top":{"pixelOffset":646.0,"sizeFraction":0.0}},"strokeAlign":"OUTSIDE","strokes":[],"effects":[],"accessibleHTMLTag":"AUTO","isDecorativeImage":false,"ariaAttributes":{},"interactions":[],"characterStyleOverrides":[],"characters":"We’d all leave the platform if there was a realistic alternative for our community","lineIndentations":[0],"lineTypes":["NONE"],"listStartOffsets":[],"lineStyleOverrides":[0],"lineTextDirections":null,"textAlignHorizontal":"RIGHT","style":{"fontFamily":"VT323","fontPostScriptName":"VT323-Regular","fontStyle":"Regular","fontVariantPosition":"NORMAL","fontSize":50.0,"textAlignHorizontal":"RIGHT","textAlignVertical":"TOP","letterSpacing":0.0,"letterSpacingValue":0.0,"letterSpacingUnit":"PERCENT","lineHeightPx":60.0,"lineHeightPercent":120.00000762939453,"lineHeightPercentFontSize":120.0,"lineHeightUnit":"PIXELS","paragraphSpacing":0,"paragraphIndent":0,"listSpacing":0,"italic":false,"textCase":"ORIGINAL","textDecoration":"NONE","textDecorationSkipInk":false,"textDecorationStyle":"solid","textAutoResize":"NONE","textTruncation":"DISABLED"},"styleOverrideTable":{}},"50:2664":{"type":"TEXT","id":"50:2664","name":"Obviously we hate supporting Meta","overrideKey":"93:181","absoluteBoundingBox":{"x":2595.0,"y":4991.0,"width":440.0,"height":234.0},"isolatedAbsoluteRenderBounds":{"x":2599.491455078125,"y":5011.16015625,"width":430.991943359375,"height":120.080078125},"relativeTransform":[[1.0,0.0,416.0],[0.0,1.0,132.0]],"size":{"x":440.0,"y":234.0},"fills":[{"blendMode":"NORMAL","type":"SOLID","color":{"r":0.0,"g":0.0,"b":0.0,"a":1.0},"visible":true,"opacity":1.0}],"constraintValues":{"left":{"pixelOffset":416.0,"sizeFraction":0.0},"top":{"pixelOffset":132.0,"sizeFraction":0.0}},"strokeAlign":"OUTSIDE","strokes":[],"effects":[],"accessibleHTMLTag":"AUTO","isDecorativeImage":false,"ariaAttributes":{},"interactions":[],"characterStyleOverrides":[],"characters":"Obviously we hate supporting Meta","lineIndentations":[0],"lineTypes":["NONE"],"listStartOffsets":[],"lineStyleOverrides":[0],"lineTextDirections":null,"textAlignHorizontal":"CENTER","style":{"fontFamily":"VT323","fontPostScriptName":"VT323-Regular","fontStyle":"Regular","fontVariantPosition":"NORMAL","fontSize":64.0,"textAlignHorizontal":"CENTER","textAlignVertical":"TOP","letterSpacing":0.0,"letterSpacingValue":0.0,"letterSpacingUnit":"PERCENT","lineHeightPx":74.0,"lineHeightPercent":115.625,"lineHeightPercentFontSize":115.625,"lineHeightUnit":"PIXELS","paragraphSpacing":0,"paragraphIndent":0,"listSpacing":0,"italic":false,"textCase":"ORIGINAL","textDecoration":"NONE","textDecorationSkipInk":false,"textDecorationStyle":"solid","textAutoResize":"NONE","textTruncation":"DISABLED"},"styleOverrideTable":{}},"50:2662":{"type":"TEXT","id":"50:2662","name":"Outside of conventions and meetups, this community connects mostly over Instagram.","overrideKey":"74:677","absoluteBoundingBox":{"x":2297.0,"y":3809.0,"width":1058.0,"height":150.0},"isolatedAbsoluteRenderBounds":{"x":2299.303955078125,"y":3830.159912109375,"width":1038.9521484375,"height":121.080078125},"relativeTransform":[[1.0,0.0,271.0],[0.0,1.0,5074.0]],"size":{"x":1058.0,"y":150.0},"fills":[{"blendMode":"NORMAL","type":"SOLID","color":{"r":0.0,"g":0.0,"b":0.0,"a":1.0},"visible":true,"opacity":1.0}],"strokeAlign":"OUTSIDE","strokes":[],"effects":[],"accessibleHTMLTag":"AUTO","isDecorativeImage":false,"ariaAttributes":{},"interactions":[],"characterStyleOverrides":[14,14,14,14,14,14,14,14,14,14,14,14,14,14,14,14,14,14,14,14,14,14,14,14,14,14,14,14,14,14,14,14,14,14,14,14,14,14,14,14,14,14,14,14,14,14,14,14,14,14,14,14,14,14,14,14,14,14,14,14,14,14,14,14,14,14,14,14,14,14,14,14,13,13,13,13,13,13,13,13,13,14],"characters":"Outside of conventions and meetups, this community connects mostly over Instagram.","lineIndentations":[0],"lineTypes":["NONE"],"listStartOffsets":[],"lineStyleOverrides":[0],"lineTextDirections":null,"textAutoResize":"HEIGHT","style":{"fontFamily":"VT323","fontPostScriptName":"VT323-Regular","fontStyle":"Regular","textAutoResize":"HEIGHT","fontVariantPosition":"NORMAL","fontSize":64.0,"textAlignHorizontal":"LEFT","textAlignVertical":"TOP","letterSpacing":0.0,"letterSpacingValue":0.0,"letterSpacingUnit":"PERCENT","lineHeightPx":75.0,"lineHeightPercent":117.1875,"lineHeightPercentFontSize":117.1875,"lineHeightUnit":"PIXELS","paragraphSpacing":0,"paragraphIndent":0,"listSpacing":0,"italic":false,"textCase":"ORIGINAL","textDecoration":"NONE","textDecorationSkipInk":false,"textDecorationStyle":"solid","textTruncation":"DISABLED"},"styleOverrideTable":{"14":{"lineHeightPx":75.0,"lineHeightPercent":100.0,"lineHeightPercentFontSize":117.1875,"lineHeightUnit":"PIXELS","paragraphSpacing":0,"paragraphIndent":0,"listSpacing":0,"italic":false,"textCase":"ORIGINAL","textDecoration":"NONE","textDecorationSkipInk":false,"textDecorationStyle":"solid","textAutoResize":"NONE","textTruncation":"DISABLED"},"13":{"fontSize":64.0,"fills":[{"blendMode":"NORMAL","type":"SOLID","color":{"r":0.9710599184036255,"g":0.12678050994873047,"b":0.12678050994873047,"a":1.0},"visible":true,"opacity":1.0}],"lineHeightPx":75.0,"lineHeightPercent":100.0,"lineHeightPercentFontSize":117.1875,"lineHeightUnit":"PIXELS","paragraphSpacing":0,"paragraphIndent":0,"listSpacing":0,"italic":false,"textCase":"ORIGINAL","textDecoration":"NONE","textDecorationSkipInk":false,"textDecorationStyle":"solid","textAutoResize":"NONE","textTruncation":"DISABLED"}}},"50:2671":{"type":"TEXT","id":"50:2671","name":"But in addition to “Meta sucks,” Instagram the product has these problems too:","overrideKey":"99:206","absoluteBoundingBox":{"x":2152.0,"y":7274.0,"width":347.0,"height":427.0},"isolatedAbsoluteRenderBounds":{"x":2160.468017578125,"y":7291.0,"width":336.71240234375,"height":276.0},"relativeTransform":[[1.0,0.0,-27.0],[0.0,1.0,723.0]],"size":{"x":347.0,"y":427.0},"fills":[{"blendMode":"NORMAL","type":"SOLID","color":{"r":0.0,"g":0.0,"b":0.0,"a":1.0},"visible":true,"opacity":1.0}],"constraintValues":{"left":{"pixelOffset":-27.0,"sizeFraction":0.0},"top":{"pixelOffset":723.0,"sizeFraction":0.0}},"strokeAlign":"OUTSIDE","strokes":[],"effects":[],"accessibleHTMLTag":"AUTO","isDecorativeImage":false,"ariaAttributes":{},"interactions":[],"characterStyleOverrides":[],"characters":"But in addition to “Meta sucks,”\nInstagram the product has these problems too:","lineIndentations":[0,0],"lineTypes":["NONE","NONE"],"listStartOffsets":[],"lineStyleOverrides":[0,0],"lineTextDirections":null,"textAlignHorizontal":"RIGHT","style":{"fontFamily":"VT323","fontPostScriptName":"VT323-Regular","fontStyle":"Regular","fontVariantPosition":"NORMAL","fontSize":50.0,"textAlignHorizontal":"RIGHT","textAlignVertical":"TOP","letterSpacing":0.0,"letterSpacingValue":0.0,"letterSpacingUnit":"PERCENT","lineHeightPx":60.0,"lineHeightPercent":120.00000762939453,"lineHeightPercentFontSize":120.0,"lineHeightUnit":"PIXELS","paragraphSpacing":0,"paragraphIndent":0,"listSpacing":0,"italic":false,"textCase":"ORIGINAL","textDecoration":"NONE","textDecorationSkipInk":false,"textDecorationStyle":"solid","textAutoResize":"NONE","textTruncation":"DISABLED"},"styleOverrideTable":{}},"50:2660":{"type":"RECTANGLE","id":"50:2660","name":"image 40","overrideKey":"74:650","absoluteBoundingBox":{"x":2151.0,"y":906.0,"width":605.0,"height":491.0},"targetAspectRatio":{"x":1024.0,"y":831.0},"isolatedAbsoluteRenderBounds":{"x":2151.0,"y":906.0,"width":605.0,"height":491.0},"relativeTransform":[[1.0,0.0,125.0],[0.0,1.0,578.0]],"size":{"x":605.0,"y":491.0},"fills":[{"blendMode":"NORMAL","type":"IMAGE","scaleMode":"FILL","imageRef":"06d4b42238051ba8c9e64e25ca42537644601449","originalImageWidth":1024,"originalImageHeight":831,"visible":true,"opacity":1.0,"rotation":0.0}],"constraintValues":{"left":{"pixelOffset":125.0,"sizeFraction":0.0},"top":{"pixelOffset":578.0,"sizeFraction":0.0}},"strokeAlign":"INSIDE","strokes":[],"effects":[],"accessibleHTMLTag":"AUTO","isDecorativeImage":false,"ariaAttributes":{},"interactions":[]},"50:2655":{"type":"RECTANGLE","id":"50:2655","name":"image 43","overrideKey":"74:661","absoluteBoundingBox":{"x":1958.0,"y":2365.0,"width":420.0,"height":345.0},"targetAspectRatio":{"x":1024.0,"y":842.0},"isolatedAbsoluteRenderBounds":{"x":1958.0,"y":2365.0,"width":420.0,"height":345.0},"relativeTransform":[[1.0,0.0,0.0],[0.0,1.0,0.0]],"size":{"x":420.0,"y":345.0},"fills":[{"blendMode":"NORMAL","type":"IMAGE","scaleMode":"FILL","imageRef":"d694aca7360065ca505577dabae57d725367d230","originalImageWidth":1024,"originalImageHeight":842,"visible":true,"opacity":1.0,"rotation":0.0}],"strokeAlign":"INSIDE","strokes":[],"effects":[],"accessibleHTMLTag":"AUTO","isDecorativeImage":false,"ariaAttributes":{},"interactions":[]},"50:2650":{"type":"TEXT","id":"50:2650","name":"The analog journaling community is HUGE, international, and growing (These aren’t my journals; they are examples of the craft!)","overrideKey":"74:645","absoluteBoundingBox":{"x":2136.0,"y":349.0,"width":737.0,"height":472.0},"isolatedAbsoluteRenderBounds":{"x":2138.52001953125,"y":375.79998779296875,"width":723.6435546875,"height":431.20001220703125},"relativeTransform":[[1.0,0.0,110.0],[0.0,1.0,21.0]],"size":{"x":737.0,"y":472.0},"fills":[{"blendMode":"NORMAL","type":"SOLID","color":{"r":0.0,"g":0.0,"b":0.0,"a":1.0},"visible":true,"opacity":1.0}],"constraintValues":{"left":{"pixelOffset":110.0,"sizeFraction":0.0},"top":{"pixelOffset":21.0,"sizeFraction":0.0}},"strokeAlign":"OUTSIDE","strokes":[],"effects":[],"accessibleHTMLTag":"AUTO","isDecorativeImage":false,"ariaAttributes":{},"interactions":[],"characterStyleOverrides":[40,40,40,40,40,40,40,40,40,40,40,40,40,40,40,40,40,40,40,40,40,40,40,40,40,40,40,40,40,40,40,40,40,40,40,39,39,39,39,40,40,39,39,39,39,39,39,39,39,39,39,39,39,39,40,40,40,40,40,40,39,39,39,39,39,39,39,39,0,38,38,38,38,38,38,38,38,38,38,38,38,38,38,38,38,38,38,38,38,38,38,38,38,38,38,38,38,38,38,38,38,38,38,38,38,38,38,38,38,38,38,38,38,38,38,38,38,38,38,38,38,38,38,38,38,38,38,38,38,38],"characters":"The analog journaling community is HUGE, international, and growing\n\n(These aren’t my journals; \n they are examples of the craft!)","lineIndentations":[0,0,0,0],"lineTypes":["NONE","NONE","NONE","NONE"],"listStartOffsets":[],"lineStyleOverrides":[0,0,0,0],"lineTextDirections":null,"style":{"fontFamily":"VT323","fontPostScriptName":"VT323-Regular","fontStyle":"Regular","fontVariantPosition":"NORMAL","fontSize":80.0,"textAlignHorizontal":"LEFT","textAlignVertical":"TOP","letterSpacing":0.0,"letterSpacingValue":0.0,"letterSpacingUnit":"PERCENT","lineHeightPx":90.0,"lineHeightPercent":112.5,"lineHeightPercentFontSize":112.5,"lineHeightUnit":"PIXELS","paragraphSpacing":0,"paragraphIndent":0,"listSpacing":0,"italic":false,"textCase":"ORIGINAL","textDecoration":"NONE","textDecorationSkipInk":false,"textDecorationStyle":"solid","textAutoResize":"NONE","textTruncation":"DISABLED"},"styleOverrideTable":{"40":{"fontSize":70.0,"paragraphSpacing":0,"paragraphIndent":0,"listSpacing":0,"italic":false,"textCase":"ORIGINAL","textDecoration":"NONE","textDecorationSkipInk":false,"textDecorationStyle":"solid","textAutoResize":"NONE","textTruncation":"DISABLED","lineHeightPercent":100,"lineHeightPercentFontSize":100},"39":{"fontSize":70.0,"fills":[{"blendMode":"NORMAL","type":"SOLID","color":{"r":0.07450980693101883,"g":0.20000000298023224,"b":0.800000011920929,"a":1.0},"visible":true,"opacity":1.0}],"paragraphSpacing":0,"paragraphIndent":0,"listSpacing":0,"italic":false,"textCase":"ORIGINAL","textDecoration":"NONE","textDecorationSkipInk":false,"textDecorationStyle":"solid","textAutoResize":"NONE","textTruncation":"DISABLED","lineHeightPercent":100,"lineHeightPercentFontSize":100},"38":{"fontSize":50.0,"fills":[{"blendMode":"NORMAL","type":"SOLID","color":{"r":0.11940062791109085,"g":0.5249211192131042,"b":0.5107749700546265,"a":1.0},"visible":true,"opacity":1.0}],"lineHeightPx":57.0,"lineHeightPercent":97.27999877929688,"lineHeightPercentFontSize":114.0,"lineHeightUnit":"PIXELS","paragraphSpacing":0,"paragraphIndent":0,"listSpacing":0,"italic":false,"textCase":"ORIGINAL","textDecoration":"NONE","textDecorationSkipInk":false,"textDecorationStyle":"solid","textAutoResize":"NONE","textTruncation":"DISABLED"}}},"50:2648":{"type":"TEXT","id":"50:2648","name":"Problem: Staying connected with the analog community","overrideKey":"74:614","absoluteBoundingBox":{"x":2171.0,"y":-1030.0,"width":1310.0,"height":458.0},"isolatedAbsoluteRenderBounds":{"x":2378.800537109375,"y":-988.2000122070312,"width":894.36376953125,"height":273.60003662109375},"relativeTransform":[[1.0,0.0,145.0],[0.0,1.0,235.0]],"size":{"x":1310.0,"y":458.0},"fills":[{"blendMode":"NORMAL","type":"SOLID","color":{"r":0.0,"g":0.0,"b":0.0,"a":1.0},"visible":true,"opacity":1.0}],"strokeAlign":"OUTSIDE","strokes":[],"effects":[],"accessibleHTMLTag":"AUTO","isDecorativeImage":false,"ariaAttributes":{},"interactions":[],"characterStyleOverrides":[29,29,29,29,29,29,29,29,29,31,31,31,31,31,31,31,31,31,31,31,31,31,31,31,31,31,31,31,31,31,31,31,31,31,31,31,31,31,31,31,31,31,31,31,31,31,31,31,31,31,31,31,31],"characters":"Problem:\nStaying connected \nwith the analog community","lineIndentations":[0,0,0],"lineTypes":["NONE","NONE","NONE"],"listStartOffsets":[],"lineStyleOverrides":[0,0,0],"lineTextDirections":null,"textAlignHorizontal":"CENTER","style":{"fontFamily":"VT323","fontPostScriptName":"VT323-Regular","fontStyle":"Regular","fontVariantPosition":"NORMAL","fontSize":100.0,"textAlignHorizontal":"CENTER","textAlignVertical":"TOP","letterSpacing":0.0,"letterSpacingValue":0.0,"letterSpacingUnit":"PERCENT","lineHeightPx":120.0,"lineHeightPercent":120.00000762939453,"lineHeightPercentFontSize":120.0,"lineHeightUnit":"PIXELS","paragraphSpacing":0,"paragraphIndent":0,"listSpacing":0,"italic":false,"textCase":"ORIGINAL","textDecoration":"NONE","textDecorationSkipInk":false,"textDecorationStyle":"solid","textAutoResize":"NONE","textTruncation":"DISABLED"},"styleOverrideTable":{"31":{"fontSize":90.0,"lineHeightPx":110.0,"lineHeightPercent":104.2962875366211,"lineHeightPercentFontSize":122.22222137451172,"lineHeightUnit":"PIXELS","paragraphSpacing":0,"paragraphIndent":0,"listSpacing":0,"italic":false,"textCase":"ORIGINAL","textDecoration":"NONE","textDecorationSkipInk":false,"textDecorationStyle":"solid","textAutoResize":"NONE","textTruncation":"DISABLED"},"29":{"fontSize":70.0,"paragraphSpacing":0,"paragraphIndent":0,"listSpacing":0,"italic":false,"textCase":"ORIGINAL","textDecoration":"NONE","textDecorationSkipInk":false,"textDecorationStyle":"solid","textAutoResize":"NONE","textTruncation":"DISABLED","lineHeightPercent":100,"lineHeightPercentFontSize":100}}},"15:1236":{"type":"FRAME","id":"15:1236","name":"Frame 9","overrideKey":"15:1236","absoluteBoundingBox":{"x":7560.5,"y":4100.0,"width":1169.0,"height":245.0},"isolatedAbsoluteRenderBounds":{"x":7560.5,"y":4100.0,"width":1169.0,"height":245.0},"relativeTransform":[[1.0,0.0,215.5],[0.0,1.0,631.0]],"size":{"x":1169.0,"y":245.0},"fills":[{"blendMode":"NORMAL","type":"SOLID","color":{"r":0.0,"g":0.0,"b":0.0,"a":1.0},"boundVariables":{"color":{"type":"VARIABLE_ALIAS","id":"VariableID:8033d4f0114a6e3fe444b55321be870ebb679842/18:2"}},"visible":true,"opacity":1.0}],"strokeAlign":"INSIDE","strokes":[],"strokeWeight":15.0,"effects":[],"boundVariables":{"fills":[{"type":"VARIABLE_ALIAS","id":"VariableID:8033d4f0114a6e3fe444b55321be870ebb679842/18:2"}]},"accessibleHTMLTag":"AUTO","isDecorativeImage":false,"ariaAttributes":{},"interactions":[{"id":{"sessionID":5,"localID":58},"event":{"interactionType":"ON_CLICK"},"actions":[{"transitionNodeID":{"sessionID":16,"localID":1410},"connectionType":"INTERNAL_NODE","navigationType":"NAVIGATE","connectionURL":"/slide-6"}],"isDeleted":false,"stateManagementVersion":1}],"paddingRight":200.0,"paddingLeft":200.0,"layoutMode":"HORIZONTAL","counterAxisAlignItems":"CENTER","primaryAxisAlignItems":"CENTER","primaryAxisSizingMode":"FIXED","counterAxisSizingMode":"FIXED","children":["15:1237"]},"15:1237":{"type":"TEXT","id":"15:1237","name":"MY PROCESS","overrideKey":"15:1237","absoluteBoundingBox":{"x":8016.5,"y":4183.0,"width":257.0,"height":79.0},"isolatedAbsoluteRenderBounds":{"x":8016.875,"y":4206.16015625,"width":256.224609375,"height":48.57568359375},"relativeTransform":[[1.0,0.0,456.0],[0.0,1.0,83.0]],"size":{"x":257.0,"y":79.0},"fills":[{"blendMode":"NORMAL","type":"SOLID","color":{"r":1.0,"g":1.0,"b":1.0,"a":1.0},"visible":true,"opacity":1.0}],"strokeAlign":"OUTSIDE","strokes":[],"effects":[],"accessibleHTMLTag":"AUTO","isDecorativeImage":false,"ariaAttributes":{},"interactions":[],"characterStyleOverrides":[],"characters":"MY PROCESS","lineIndentations":[0],"lineTypes":["NONE"],"listStartOffsets":[],"lineStyleOverrides":[0],"lineTextDirections":null,"textAutoResize":"WIDTH_AND_HEIGHT","textAlignHorizontal":"CENTER","style":{"fontFamily":"VT323","fontPostScriptName":"VT323-Regular","fontStyle":"Regular","hyperlink":{"type":"NODE","nodeID":"/slide-6"},"textAutoResize":"WIDTH_AND_HEIGHT","fontVariantPosition":"NORMAL","textDecoration":"UNDERLINE","textDecorationSkipInk":true,"fontSize":64.0,"textAlignHorizontal":"CENTER","textAlignVertical":"TOP","letterSpacing":0.0,"letterSpacingValue":0.0,"letterSpacingUnit":"PERCENT","lineHeightPx":79.0,"lineHeightPercent":123.4375,"lineHeightPercentFontSize":123.4375,"lineHeightUnit":"PIXELS","paragraphSpacing":0,"paragraphIndent":0,"listSpacing":0,"italic":false,"textCase":"ORIGINAL","textDecorationStyle":"solid","textTruncation":"DISABLED"},"styleOverrideTable":{}},"50:2721":{"type":"FRAME","id":"50:2721","name":"Frame 46","overrideKey":"74:744","absoluteBoundingBox":{"x":2063.5,"y":12091.0,"width":1525.0,"height":1190.0},"isolatedAbsoluteRenderBounds":{"x":2063.5,"y":12091.0,"width":1525.0,"height":1190.0},"relativeTransform":[[1.0,0.0,37.5],[0.0,1.0,13356.0]],"size":{"x":1525.0,"y":1190.0},"fills":[],"strokeAlign":"INSIDE","strokes":[],"effects":[],"accessibleHTMLTag":"AUTO","isDecorativeImage":false,"ariaAttributes":{},"interactions":[],"children":["50:2722","50:2723","50:2739","50:2742"]},"50:2695":{"type":"TEXT","id":"50:2695","name":"Seeing these problems, I thought to myself:","overrideKey":"74:682","absoluteBoundingBox":{"x":2130.0,"y":8917.0,"width":1392.0,"height":142.0},"isolatedAbsoluteRenderBounds":{"x":2311.656005859375,"y":8961.400390625,"width":1022.064453125,"height":43.19921875},"relativeTransform":[[1.0,0.0,120.0],[0.0,1.0,0.0]],"size":{"x":1392.0,"y":142.0},"fills":[{"blendMode":"NORMAL","type":"SOLID","color":{"r":0.0,"g":0.0,"b":0.0,"a":1.0},"visible":true,"opacity":1.0}],"constraints":{"vertical":"TOP","horizontal":"CENTER"},"constraintValues":{"left":{"pixelOffset":-696.0,"sizeFraction":0.5},"right":{"pixelOffset":696.0,"sizeFraction":0.5},"top":{"pixelOffset":0.0,"sizeFraction":0.0}},"strokeAlign":"OUTSIDE","strokes":[],"effects":[],"accessibleHTMLTag":"AUTO","isDecorativeImage":false,"ariaAttributes":{},"interactions":[],"characterStyleOverrides":[],"characters":"Seeing these problems, I thought to myself:","lineIndentations":[0],"lineTypes":["NONE"],"listStartOffsets":[],"lineStyleOverrides":[0],"lineTextDirections":null,"textAlignHorizontal":"CENTER","style":{"fontFamily":"VT323","fontPostScriptName":"VT323-Regular","fontStyle":"Regular","fontVariantPosition":"NORMAL","fontSize":60.0,"textAlignHorizontal":"CENTER","textAlignVertical":"TOP","letterSpacing":0.0,"letterSpacingValue":0.0,"letterSpacingUnit":"PERCENT","lineHeightPx":120.0,"lineHeightPercent":200.0,"lineHeightPercentFontSize":200.0,"lineHeightUnit":"PIXELS","paragraphSpacing":0,"paragraphIndent":0,"listSpacing":0,"italic":false,"textCase":"ORIGINAL","textDecoration":"NONE","textDecorationSkipInk":false,"textDecorationStyle":"solid","textAutoResize":"NONE","textTruncation":"DISABLED"},"styleOverrideTable":{}},"50:2702":{"type":"RECTANGLE","id":"50:2702","name":"image 47","overrideKey":"99:361","absoluteBoundingBox":{"x":2147.0,"y":10738.0,"width":439.0,"height":453.0},"targetAspectRatio":{"x":858.0,"y":886.0},"isolatedAbsoluteRenderBounds":{"x":2147.0,"y":10738.0,"width":439.0,"height":453.0},"relativeTransform":[[1.0,0.0,149.0],[0.0,1.0,316.0]],"size":{"x":439.0,"y":453.0},"fills":[{"blendMode":"NORMAL","type":"IMAGE","scaleMode":"FILL","imageRef":"ab920b0f26621e113e5411c1bbf88b324f20cc48","originalImageWidth":858,"originalImageHeight":886,"visible":true,"opacity":1.0,"rotation":0.0}],"constraintValues":{"left":{"pixelOffset":149.0,"sizeFraction":0.0},"top":{"pixelOffset":316.0,"sizeFraction":0.0}},"strokeAlign":"INSIDE","strokes":[],"effects":[],"accessibleHTMLTag":"AUTO","isDecorativeImage":false,"ariaAttributes":{},"interactions":[]},"50:2661":{"type":"RECTANGLE","id":"50:2661","name":"image 41","overrideKey":"74:653","absoluteBoundingBox":{"x":2846.0,"y":1046.0,"width":639.0,"height":539.0},"targetAspectRatio":{"x":1336.0,"y":1126.0},"isolatedAbsoluteRenderBounds":{"x":2846.0,"y":1046.0,"width":639.0,"height":539.0},"relativeTransform":[[1.0,0.0,820.0],[0.0,1.0,718.0]],"size":{"x":639.0,"y":539.0},"fills":[{"blendMode":"NORMAL","type":"IMAGE","scaleMode":"FILL","imageRef":"5cefdeee8f4764d2d1026aa3b3468460f2f8665e","originalImageWidth":1336,"originalImageHeight":1126,"visible":true,"opacity":1.0,"rotation":0.0}],"constraintValues":{"left":{"pixelOffset":820.0,"sizeFraction":0.0},"top":{"pixelOffset":718.0,"sizeFraction":0.0}},"strokeAlign":"INSIDE","strokes":[],"effects":[],"accessibleHTMLTag":"AUTO","isDecorativeImage":false,"ariaAttributes":{},"interactions":[]},"50:2722":{"type":"RECTANGLE","id":"50:2722","name":"image 49","overrideKey":"74:702","absoluteBoundingBox":{"x":2064.0,"y":12171.000047135954,"width":590.1695076491151,"height":493.9331699846789},"targetAspectRatio":{"x":1024.0,"y":776.0},"isolatedAbsoluteRenderBounds":{"x":2064.0,"y":12171.0,"width":590.16943359375,"height":493.93359375},"relativeTransform":[[0.9773929119110107,0.2114311307668686,0.5],[-0.2114311307668686,0.9773929119110107,189.6855010986328]],"size":{"x":518.7764892578125,"y":393.13531494140625},"fills":[{"blendMode":"NORMAL","type":"IMAGE","scaleMode":"FILL","imageRef":"3a6409c8883d64eae5e7cf47e9ccd0c9f2779068","originalImageWidth":1024,"originalImageHeight":776,"visible":true,"opacity":1.0,"rotation":0.0}],"constraintValues":{"left":{"pixelOffset":0.5,"sizeFraction":0.0},"top":{"pixelOffset":80.00000135958726,"sizeFraction":0.0}},"strokeAlign":"INSIDE","strokes":[],"effects":[],"accessibleHTMLTag":"AUTO","isDecorativeImage":false,"ariaAttributes":{},"interactions":[]},"50:2654":{"type":"FRAME","id":"50:2654","name":"Frame 42","overrideKey":"74:672","absoluteBoundingBox":{"x":1958.0,"y":2365.0,"width":1737.0,"height":345.0},"isolatedAbsoluteRenderBounds":{"x":1958.0,"y":2365.0,"width":1737.0,"height":345.0},"relativeTransform":[[1.0,0.0,-68.0],[0.0,1.0,2037.0]],"size":{"x":1737.0,"y":345.0},"fills":[],"constraints":{"vertical":"TOP","horizontal":"CENTER"},"constraintValues":{"left":{"pixelOffset":-868.0,"sizeFraction":0.5},"right":{"pixelOffset":869.0,"sizeFraction":0.5},"top":{"pixelOffset":2037.0,"sizeFraction":0.0}},"strokeAlign":"INSIDE","strokes":[],"effects":[],"accessibleHTMLTag":"AUTO","isDecorativeImage":false,"ariaAttributes":{},"interactions":[],"layoutMode":"HORIZONTAL","itemSpacing":5.0,"counterAxisAlignItems":"CENTER","primaryAxisAlignItems":"CENTER","children":["50:2655","50:2656","50:2657","50:2658"]},"50:2675":{"type":"RECTANGLE","id":"50:2675","name":"Rectangle 1","overrideKey":"99:294","absoluteBoundingBox":{"x":2763.0,"y":6618.0,"width":679.0,"height":481.0},"isolatedAbsoluteRenderBounds":{"x":2763.0,"y":6618.0,"width":679.0,"height":481.0},"relativeTransform":[[1.0,0.0,16.0],[0.0,1.0,15.0]],"size":{"x":679.0,"y":481.0},"fills":[{"blendMode":"NORMAL","type":"SOLID","color":{"r":0.95686274766922,"g":1.0,"b":0.7647058963775635,"a":1.0},"visible":true,"opacity":1.0}],"constraints":{"vertical":"SCALE","horizontal":"SCALE"},"constraintValues":{"left":{"pixelOffset":0.0,"sizeFraction":0.022723612310958017},"right":{"pixelOffset":0.0,"sizeFraction":0.9870569097572388},"top":{"pixelOffset":-1.7763568394002505e-15,"sizeFraction":0.02325183145071333},"bottom":{"pixelOffset":0.0,"sizeFraction":0.768860559970254}},"strokeAlign":"INSIDE","strokes":[],"effects":[],"accessibleHTMLTag":"AUTO","isDecorativeImage":false,"ariaAttributes":{},"interactions":[]},"50:2649":{"type":"FRAME","id":"50:2649","name":"Frame 43","overrideKey":"74:675","absoluteBoundingBox":{"x":2026.0,"y":328.0,"width":1600.0,"height":2581.0},"isolatedAbsoluteRenderBounds":{"x":1958.0,"y":328.0,"width":1737.0,"height":2581.0},"relativeTransform":[[1.0,0.0,0.0],[0.0,1.0,1593.0]],"size":{"x":1600.0,"y":2581.0},"fills":[],"strokeAlign":"INSIDE","layoutAlign":"STRETCH","strokes":[],"effects":[],"accessibleHTMLTag":"AUTO","isDecorativeImage":false,"ariaAttributes":{},"interactions":[],"children":["50:2650","50:2651","50:2652","50:2653","50:2654","50:2659","50:2660","50:2661"]},"50:2697":{"type":"RECTANGLE","id":"50:2697","name":"image 48","overrideKey":"74:688","absoluteBoundingBox":{"x":2589.0,"y":9036.0,"width":791.0,"height":432.0},"targetAspectRatio":{"x":2048.0,"y":1117.0},"isolatedAbsoluteRenderBounds":{"x":2589.0,"y":9036.0,"width":791.0,"height":432.0},"relativeTransform":[[1.0,0.0,579.0],[0.0,1.0,119.0]],"size":{"x":791.0,"y":432.0},"fills":[{"blendMode":"NORMAL","type":"IMAGE","scaleMode":"FILL","imageRef":"40161369bf6fe385afffb3f01db62d408e0698a2","originalImageWidth":2048,"originalImageHeight":1117,"visible":true,"opacity":1.0,"rotation":0.0}],"constraintValues":{"left":{"pixelOffset":579.0,"sizeFraction":0.0},"top":{"pixelOffset":119.0,"sizeFraction":0.0}},"strokeAlign":"INSIDE","strokes":[],"effects":[],"accessibleHTMLTag":"AUTO","isDecorativeImage":false,"ariaAttributes":{},"interactions":[]},"15:1233":{"type":"FRAME","id":"15:1233","name":"Desktop","overrideKey":"15:1233","absoluteBoundingBox":{"x":7345.0,"y":-11312.0,"width":1600.0,"height":16149.0},"isolatedAbsoluteRenderBounds":{"x":7345.0,"y":-11312.0,"width":1600.0,"height":16149.0},"relativeTransform":[[1.0,0.0,64.0],[0.0,1.0,100.0]],"size":{"x":1600.0,"y":16149.0},"fills":[{"blendMode":"NORMAL","type":"SOLID","color":{"r":0.5098039507865906,"g":0.8470588326454163,"b":0.8352941274642944,"a":1.0},"visible":true,"opacity":1.0}],"strokeAlign":"INSIDE","strokes":[],"effects":[],"accessibleHTMLTag":"AUTO","isDecorativeImage":false,"ariaAttributes":{},"interactions":[],"clipsContent":true,"overflowDirection":"VERTICAL_SCROLLING","layoutMode":"VERTICAL","counterAxisAlignItems":"CENTER","counterAxisSizingMode":"FIXED","isBreakpointFrame":true,"children":["15:1343","15:1235"]},"50:2658":{"type":"RECTANGLE","id":"50:2658","name":"image 46","overrideKey":"74:670","absoluteBoundingBox":{"x":3329.0,"y":2400.0,"width":366.0,"height":275.0},"targetAspectRatio":{"x":366.0,"y":275.0},"isolatedAbsoluteRenderBounds":{"x":3329.0,"y":2400.0,"width":366.0,"height":275.0},"relativeTransform":[[1.0,0.0,1371.0],[0.0,1.0,35.0]],"size":{"x":366.0,"y":275.0},"fills":[{"blendMode":"NORMAL","type":"IMAGE","scaleMode":"STRETCH","imageRef":"c6b6bb61a406f48e2508764d0bf6f83d2297264a","imageTransform":[[1.0,0.0,0.007664624135941267],[0.0,0.751366138458252,0.08735993504524231]],"originalImageWidth":778,"originalImageHeight":778,"visible":true,"opacity":1.0,"rotation":0.0}],"strokeAlign":"INSIDE","strokes":[],"effects":[],"accessibleHTMLTag":"AUTO","isDecorativeImage":false,"ariaAttributes":{},"interactions":[]},"50:2656":{"type":"RECTANGLE","id":"50:2656","name":"image 44","overrideKey":"74:664","absoluteBoundingBox":{"x":2383.0,"y":2382.5,"width":492.0,"height":310.0},"targetAspectRatio":{"x":1024.0,"y":645.0},"isolatedAbsoluteRenderBounds":{"x":2383.0,"y":2382.5,"width":492.0,"height":310.0},"relativeTransform":[[1.0,0.0,425.0],[0.0,1.0,17.5]],"size":{"x":492.0,"y":310.0},"fills":[{"blendMode":"NORMAL","type":"IMAGE","scaleMode":"FILL","imageRef":"00cb0963c8130f92de196bc72818213bc75a16f2","originalImageWidth":1024,"originalImageHeight":645,"visible":true,"opacity":1.0,"rotation":0.0}],"strokeAlign":"INSIDE","strokes":[],"effects":[],"accessibleHTMLTag":"AUTO","isDecorativeImage":false,"ariaAttributes":{},"interactions":[]},"15:1235":{"type":"FRAME","id":"15:1235","name":"SLIDE 1 NAVI","overrideKey":"15:1235","absoluteBoundingBox":{"x":7345.0,"y":3469.0,"width":1600.0,"height":1368.0},"isolatedAbsoluteRenderBounds":{"x":7345.0,"y":3469.0,"width":1600.0,"height":1368.0},"relativeTransform":[[1.0,0.0,0.0],[0.0,1.0,14781.0]],"size":{"x":1600.0,"y":1368.0},"fills":[{"blendMode":"NORMAL","type":"SOLID","color":{"r":0.5098039507865906,"g":0.8470588326454163,"b":0.8352941274642944,"a":1.0},"visible":true,"opacity":1.0}],"strokeAlign":"INSIDE","layoutAlign":"STRETCH","strokes":[],"effects":[],"accessibleHTMLTag":"AUTO","isDecorativeImage":false,"ariaAttributes":{},"interactions":[],"paddingTop":366.0,"paddingRight":215.0,"paddingBottom":366.0,"paddingLeft":215.0,"layoutMode":"VERTICAL","itemSpacing":52.0,"counterAxisAlignItems":"CENTER","primaryAxisSizingMode":"FIXED","counterAxisSizingMode":"FIXED","children":["15:1238","15:1236"]},"50:2647":{"type":"COMPONENT","id":"50:2647","name":"SLIDE 5","overrideKey":"74:748","absoluteBoundingBox":{"x":2026.0,"y":-1265.0,"width":1600.0,"height":14781.0},"isolatedAbsoluteRenderBounds":{"x":1958.0,"y":-1265.0,"width":1737.0,"height":14781.0},"relativeTransform":[[1.0,0.0,2026.0],[0.0,1.0,-1265.0]],"size":{"x":1600.0,"y":14781.0},"fills":[{"blendMode":"NORMAL","type":"SOLID","color":{"r":0.5098039507865906,"g":0.8470588326454163,"b":0.8352941274642944,"a":1.0},"visible":true,"opacity":1.0}],"strokeAlign":"INSIDE","strokes":[],"effects":[],"accessibleHTMLTag":"AUTO","isDecorativeImage":false,"ariaAttributes":{},"interactions":[],"paddingTop":235.0,"paddingBottom":235.0,"layoutMode":"VERTICAL","itemSpacing":900.0,"counterAxisAlignItems":"CENTER","counterAxisSizingMode":"FIXED","children":["50:2648","50:2649","50:2662","50:2663","50:2670","50:2693","50:2721"]},"50:2739":{"type":"SVG","id":"50:2739","name":"Group 4","overrideKey":"74:743","absoluteBoundingBox":{"x":2117.640625,"y":12564.0,"width":538.3924560546875,"height":211.54891967773438},"isolatedAbsoluteRenderBounds":{"x":2112.639404296875,"y":12559.0,"width":548.3935546875,"height":221.5498046875},"relativeTransform":[[1.0,0.0,54.140625],[0.0,1.0,472.99993896484375]],"size":{"x":538.3924560546875,"y":211.54891967773438},"fills":[],"constraintValues":{"left":{"pixelOffset":54.140625,"sizeFraction":0.0},"top":{"pixelOffset":472.99993896484375,"sizeFraction":0.0}},"strokeAlign":"INSIDE","strokes":[],"accessibleHTMLTag":"AUTO","isDecorativeImage":false,"ariaAttributes":{},"interactions":[],"hash":"f988913985c9e710495e2cdf2e4b29bccf1ce074"},"50:2692":{"type":"TEXT","id":"50:2692","name":"Problems with Instagram: 📱 Inspiration you never revisit 📱 TOO MUCH CONTENT, feel behind 📱 Feeling inadequate 📱 Need a “following” to be seen 📱 On your phone when you wanna be in your journal","overrideKey":"99:325","absoluteBoundingBox":{"x":2613.8232421875,"y":7281.84716796875,"width":808.0,"height":537.2732543945312},"isolatedAbsoluteRenderBounds":{"x":2613.8232421875,"y":7304.2470703125,"width":778.519775390625,"height":493.2001953125},"relativeTransform":[[1.0,0.0,73.8232421875],[0.0,1.0,63.84466552734375]],"size":{"x":808.0,"y":537.2732543945312},"fills":[{"blendMode":"NORMAL","type":"SOLID","color":{"r":0.0,"g":0.0,"b":0.0,"a":1.0},"visible":true,"opacity":1.0}],"constraints":{"vertical":"SCALE","horizontal":"SCALE"},"constraintValues":{"left":{"pixelOffset":5.684341886080802e-14,"sizeFraction":0.3360303262654559},"right":{"pixelOffset":0.0,"sizeFraction":0.96045072812017},"top":{"pixelOffset":0.0,"sizeFraction":0.49853145084146916},"bottom":{"pixelOffset":0.0,"sizeFraction":0.8650207103193213}},"strokeAlign":"OUTSIDE","strokes":[],"effects":[],"accessibleHTMLTag":"AUTO","isDecorativeImage":false,"ariaAttributes":{},"interactions":[],"characterStyleOverrides":[22,22,22,22,21,21,21,21,21,21,21,21,21,21,21,21,21,21,21,21,21,21,21,21,21,21,21,21,21,22,22,22,22,22,22,22,22,22,22,22,22,22,22,22,22,22,22,22,22,22,22,22,22,22,22,22,22,22,22,22,22,22,22,22,22,22,22,22,22,22,22,22,22,22,22,22,22,22,22,22,22,22,22,22,22,22,22,22,22,22,22,22,22,22,22,22,22,22,22,22,22,22,22,22,22,22,22,22,22,22,22,22,22,22,22,22,22,22,22,22,22,22,22,22,22,22,22,22,22,22,22,22,22,22,22,22,22,22,22,22,22,22,22,22,22,22,22,22,22,22,22,22,22,22,22,22,22,22,22,22,22,22,22,22,22,22,22,22,22,22,22,22,22,22,22,22,22,22,22,22,22,22,22,22,22,22,22,22,22,22,22,22,22,22,22,22,22,22,22,22],"characters":"    Problems with Instagram:\n📱 Inspiration you never revisit\n📱 TOO MUCH CONTENT, feel behind\n📱 Feeling inadequate\n📱 Need a “following” to be seen\n📱 On your phone when you wanna\n    be in your journal\n","lineIndentations":[0,0,0,0,0,0,0,0],"lineTypes":["NONE","NONE","NONE","NONE","NONE","NONE","NONE","NONE"],"listStartOffsets":[],"lineStyleOverrides":[0,0,0,0,0,0,0,0],"lineTextDirections":null,"fallbackFonts":[{"fontFamily":"Noto Sans","fontStyle":"Regular"}],"style":{"fontFamily":"VT323","fontPostScriptName":"VT323-Regular","fontStyle":"Regular","fallbackFonts":[{"fontFamily":"Noto Sans","fontStyle":"Regular"}],"fontVariantPosition":"NORMAL","fontSize":60.0,"textAlignHorizontal":"LEFT","textAlignVertical":"TOP","letterSpacing":0.0,"letterSpacingValue":0.0,"letterSpacingUnit":"PERCENT","lineHeightPx":75.0,"lineHeightPercent":125.0,"lineHeightPercentFontSize":125.0,"lineHeightUnit":"PIXELS","paragraphSpacing":0,"paragraphIndent":0,"listSpacing":0,"italic":false,"textCase":"ORIGINAL","textDecoration":"NONE","textDecorationSkipInk":false,"textDecorationStyle":"solid","textAutoResize":"NONE","textTruncation":"DISABLED"},"styleOverrideTable":{"22":{"fallbackFonts":[{"fontFamily":"Noto Sans","fontStyle":"Regular"}],"lineHeightPx":75.0,"lineHeightPercent":106.66667175292969,"lineHeightPercentFontSize":125.0,"lineHeightUnit":"PIXELS","paragraphSpacing":0,"paragraphIndent":0,"listSpacing":0,"italic":false,"textCase":"ORIGINAL","textDecoration":"NONE","textDecorationSkipInk":false,"textDecorationStyle":"solid","textAutoResize":"NONE","textTruncation":"DISABLED"},"21":{"fallbackFonts":[{"fontFamily":"Noto Sans","fontStyle":"Regular"}],"textDecoration":"UNDERLINE","fontSize":60.0,"lineHeightPx":75.0,"lineHeightPercent":106.66667175292969,"lineHeightPercentFontSize":125.0,"lineHeightUnit":"PIXELS","paragraphSpacing":0,"paragraphIndent":0,"listSpacing":0,"italic":false,"textCase":"ORIGINAL","textDecorationSkipInk":false,"textDecorationStyle":"solid","textAutoResize":"NONE","textTruncation":"DISABLED"}}},"1:2":{"id":"1:2","assetId":"VariableCollectionId:7c5f5a79620c1c68e6e553b7b51078dd6262a5d7/18:0","type":"VARIABLE_COLLECTION","name":"Variable collection","defaultModeId":"18:0","modes":[{"modeId":"18:0","name":"Mode 1"}]},"50:2657":{"type":"RECTANGLE","id":"50:2657","name":"image 45","overrideKey":"74:667","absoluteBoundingBox":{"x":2880.0,"y":2365.0,"width":444.0,"height":345.0},"targetAspectRatio":{"x":1024.0,"y":795.0},"isolatedAbsoluteRenderBounds":{"x":2880.0,"y":2365.0,"width":444.0,"height":345.0},"relativeTransform":[[1.0,0.0,922.0],[0.0,1.0,0.0]],"size":{"x":444.0,"y":345.0},"fills":[{"blendMode":"NORMAL","type":"IMAGE","scaleMode":"FILL","imageRef":"2357e923eb6d974b63f49518118fd7e232d69d90","originalImageWidth":1024,"originalImageHeight":795,"visible":true,"opacity":1.0,"rotation":0.0}],"strokeAlign":"INSIDE","strokes":[],"effects":[],"accessibleHTMLTag":"AUTO","isDecorativeImage":false,"ariaAttributes":{},"interactions":[]},"50:2669":{"type":"RECTANGLE","id":"50:2669","name":"CleanShot 2025-09-28 at 11.56.14@2x 1","overrideKey":"99:190","absoluteBoundingBox":{"x":2339.0,"y":5225.0,"width":452.0,"height":246.0},"targetAspectRatio":{"x":2370.0,"y":1290.0},"isolatedAbsoluteRenderBounds":{"x":2339.0,"y":5225.0,"width":452.0,"height":246.0},"relativeTransform":[[1.0,0.0,160.0],[0.0,1.0,366.0]],"size":{"x":452.0,"y":246.0},"fills":[{"blendMode":"NORMAL","type":"IMAGE","scaleMode":"FILL","imageRef":"6aeec36bd7b615a70ef49cfb80d0deb4d7741a3a","originalImageWidth":2370,"originalImageHeight":1290,"visible":true,"opacity":1.0,"rotation":0.0}],"constraintValues":{"left":{"pixelOffset":160.0,"sizeFraction":0.0},"top":{"pixelOffset":366.0,"sizeFraction":0.0}},"strokeAlign":"INSIDE","strokes":[],"effects":[],"accessibleHTMLTag":"AUTO","isDecorativeImage":false,"ariaAttributes":{},"interactions":[]},"50:2705":{"type":"SVG","id":"50:2705","name":"svgviewer-output 1","overrideKey":"99:364","absoluteBoundingBox":{"x":2743.0,"y":10666.0,"width":167.0,"height":205.0},"isolatedAbsoluteRenderBounds":{"x":2743.0,"y":10666.0,"width":167.0,"height":205.0},"relativeTransform":[[1.0,0.0,745.0],[0.0,1.0,244.0]],"size":{"x":167.0,"y":205.0},"fills":[],"constraintValues":{"left":{"pixelOffset":745.0,"sizeFraction":0.0},"top":{"pixelOffset":244.0,"sizeFraction":0.0}},"strokeAlign":"INSIDE","strokes":[],"accessibleHTMLTag":"AUTO","isDecorativeImage":false,"ariaAttributes":{},"interactions":[],"hash":"5c3f1c9592c4ed696fc55c701828672253a60586"},"50:2723":{"type":"SVG","id":"50:2723","name":"svgviewer-output 2","overrideKey":"74:720","absoluteBoundingBox":{"x":2343.0,"y":12794.0,"width":311.0,"height":381.0},"isolatedAbsoluteRenderBounds":{"x":2343.0,"y":12794.0,"width":311.0,"height":381.0},"relativeTransform":[[1.0,0.0,279.5],[0.0,1.0,702.9999389648438]],"size":{"x":311.0,"y":381.0},"fills":[],"constraintValues":{"left":{"pixelOffset":279.5,"sizeFraction":0.0},"top":{"pixelOffset":702.9999389648438,"sizeFraction":0.0}},"strokeAlign":"INSIDE","strokes":[],"accessibleHTMLTag":"AUTO","isDecorativeImage":false,"ariaAttributes":{},"interactions":[],"hash":"6bff14706552884c26074230bef9e19f0fb53ca2"},"50:2651":{"type":"TEXT","id":"50:2651","name":"Stationery \u0026 journaling has been a thing in Asia for forever, but interest has exploded in the West over the past few years.","overrideKey":"74:658","absoluteBoundingBox":{"x":2839.0,"y":1750.0,"width":691.0,"height":350.0},"isolatedAbsoluteRenderBounds":{"x":2841.159912109375,"y":1769.4000244140625,"width":643.089599609375,"height":323.2000732421875},"relativeTransform":[[1.0,0.0,813.0],[0.0,1.0,1422.0]],"size":{"x":691.0,"y":350.0},"fills":[{"blendMode":"NORMAL","type":"SOLID","color":{"r":0.0,"g":0.0,"b":0.0,"a":1.0},"visible":true,"opacity":1.0}],"constraintValues":{"left":{"pixelOffset":813.0,"sizeFraction":0.0},"top":{"pixelOffset":1422.0,"sizeFraction":0.0}},"strokeAlign":"OUTSIDE","strokes":[],"effects":[],"accessibleHTMLTag":"AUTO","isDecorativeImage":false,"ariaAttributes":{},"interactions":[],"characterStyleOverrides":[],"characters":"Stationery \u0026 journaling has been a thing in Asia for forever, but interest has exploded in the West over the past few years.","lineIndentations":[0],"lineTypes":["NONE"],"listStartOffsets":[],"lineStyleOverrides":[0],"lineTextDirections":null,"textAutoResize":"HEIGHT","style":{"fontFamily":"VT323","fontPostScriptName":"VT323-Regular","fontStyle":"Regular","textAutoResize":"HEIGHT","fontVariantPosition":"NORMAL","fontSize":60.0,"textAlignHorizontal":"LEFT","textAlignVertical":"TOP","letterSpacing":0.0,"letterSpacingValue":0.0,"letterSpacingUnit":"PERCENT","lineHeightPx":70.0,"lineHeightPercent":116.66666412353516,"lineHeightPercentFontSize":116.66666412353516,"lineHeightUnit":"PIXELS","paragraphSpacing":0,"paragraphIndent":0,"listSpacing":0,"italic":false,"textCase":"ORIGINAL","textDecoration":"NONE","textDecorationSkipInk":false,"textDecorationStyle":"solid","textTruncation":"DISABLED"},"styleOverrideTable":{}},"50:2693":{"type":"FRAME","id":"50:2693","name":"Frame 47","overrideKey":"74:747","absoluteBoundingBox":{"x":2010.0,"y":8917.0,"width":1632.0,"height":2274.0},"isolatedAbsoluteRenderBounds":{"x":1998.0,"y":8917.0,"width":1644.0,"height":2476.0},"relativeTransform":[[1.0,0.0,-16.0],[0.0,1.0,10182.0]],"size":{"x":1632.0,"y":2274.0},"fills":[],"strokeAlign":"INSIDE","strokes":[],"effects":[],"accessibleHTMLTag":"AUTO","isDecorativeImage":false,"ariaAttributes":{},"interactions":[],"children":["50:2694","50:2699","50:2700"]},"15:1232":{"type":"WEBPAGE","id":"15:1232","name":"/slide-5","overrideKey":"15:1232","absoluteBoundingBox":{"x":7281.0,"y":-11412.0,"width":1728.0,"height":16313.0},"isolatedAbsoluteRenderBounds":{"x":7281.0,"y":-11412.0,"width":1728.0,"height":16313.0},"relativeTransform":[[1.0,0.0,7281.0],[0.0,1.0,-11412.0]],"size":{"x":1728.0,"y":16313.0},"fills":[{"opacity":0.2980392277240753,"blendMode":"NORMAL","type":"SOLID","color":{"r":1.0,"g":1.0,"b":1.0,"a":1.0},"visible":true}],"strokeAlign":"INSIDE","strokes":[],"accessibleHTMLTag":"AUTO","isDecorativeImage":false,"ariaAttributes":{},"interactions":[],"children":["15:1233"]},"50:2674":{"type":"FRAME","id":"50:2674","name":"Frame 51","overrideKey":"99:293","absoluteBoundingBox":{"x":2747.0,"y":6603.0,"width":704.1134033203125,"height":645.1104736328125},"isolatedAbsoluteRenderBounds":{"x":2747.0,"y":6603.0,"width":704.113525390625,"height":645.1104736328125},"relativeTransform":[[1.0,0.0,0.0],[0.0,1.0,0.0]],"size":{"x":704.1134033203125,"y":645.1104736328125},"fills":[],"constraintValues":{"left":{"pixelOffset":568.0,"sizeFraction":0.0},"top":{"pixelOffset":52.0,"sizeFraction":0.0}},"strokeAlign":"INSIDE","strokes":[],"effects":[],"accessibleHTMLTag":"AUTO","isDecorativeImage":false,"ariaAttributes":{},"interactions":[],"children":["50:2675","50:2676","50:2682"]},"50:2653":{"type":"RECTANGLE","id":"50:2653","name":"image 42","overrideKey":"74:656","absoluteBoundingBox":{"x":2136.0,"y":1619.0,"width":636.0,"height":612.0},"targetAspectRatio":{"x":1072.0,"y":1032.0},"isolatedAbsoluteRenderBounds":{"x":2136.0,"y":1619.0,"width":636.0,"height":612.0},"relativeTransform":[[1.0,0.0,110.0],[0.0,1.0,1291.0]],"size":{"x":636.0,"y":612.0},"fills":[{"blendMode":"NORMAL","type":"IMAGE","scaleMode":"FILL","imageRef":"720d23834212e74dfdb5e0abf45fb6a106861dfd","originalImageWidth":1072,"originalImageHeight":1032,"visible":true,"opacity":1.0,"rotation":0.0}],"constraintValues":{"left":{"pixelOffset":110.0,"sizeFraction":0.0},"top":{"pixelOffset":1291.0,"sizeFraction":0.0}},"strokeAlign":"INSIDE","strokes":[],"effects":[],"accessibleHTMLTag":"AUTO","isDecorativeImage":false,"ariaAttributes":{},"interactions":[]},"15:1238":{"type":"TEXT","id":"15:1238","name":"Speedrun through the process of making Pouch Magazine:","overrideKey":"15:1238","absoluteBoundingBox":{"x":7667.5,"y":3835.0,"width":955.0,"height":213.0},"isolatedAbsoluteRenderBounds":{"x":7699.4423828125,"y":3864.199951171875,"width":889.4833984375,"height":157.60009765625},"relativeTransform":[[1.0,0.0,322.5],[0.0,1.0,366.0]],"size":{"x":955.0,"y":213.0},"fills":[{"blendMode":"NORMAL","type":"SOLID","color":{"r":0.0,"g":0.0,"b":0.0,"a":1.0},"visible":true,"opacity":1.0}],"strokeAlign":"OUTSIDE","strokes":[],"effects":[],"accessibleHTMLTag":"AUTO","isDecorativeImage":false,"ariaAttributes":{},"interactions":[],"characterStyleOverrides":[],"characters":"Speedrun through the process of making Pouch Magazine:\n","lineIndentations":[0,0],"lineTypes":["NONE","NONE"],"listStartOffsets":[],"lineStyleOverrides":[0,0],"lineTextDirections":null,"textAlignHorizontal":"CENTER","style":{"fontFamily":"VT323","fontPostScriptName":"VT323-Regular","fontStyle":"Regular","fontVariantPosition":"NORMAL","fontSize":80.0,"textAlignHorizontal":"CENTER","textAlignVertical":"TOP","letterSpacing":0.0,"letterSpacingValue":0.0,"letterSpacingUnit":"PERCENT","lineHeightPx":100.0,"lineHeightPercent":125.0,"lineHeightPercentFontSize":125.0,"lineHeightUnit":"PIXELS","paragraphSpacing":0,"paragraphIndent":0,"listSpacing":0,"italic":false,"textCase":"ORIGINAL","textDecoration":"NONE","textDecorationSkipInk":false,"textDecorationStyle":"solid","textAutoResize":"NONE","textTruncation":"DISABLED"},"styleOverrideTable":{}},"15:1343":{"mainComponentId":"50:2647","type":"INSTANCE","id":"15:1343","name":"SLIDE 5","overrideKey":"15:1343","absoluteBoundingBox":{"x":7345.0,"y":-11312.0,"width":1600.0,"height":14781.0},"isolatedAbsoluteRenderBounds":{"x":7277.0,"y":-11312.0,"width":1737.0,"height":14781.0},"relativeTransform":[[1.0,0.0,0.0],[0.0,1.0,0.0]],"size":{"x":1600.0,"y":14781.0},"fills":[{"blendMode":"NORMAL","type":"SOLID","color":{"r":0.5098039507865906,"g":0.8470588326454163,"b":0.8352941274642944,"a":1.0},"visible":true,"opacity":1.0}],"strokeAlign":"INSIDE","strokes":[],"effects":[],"accessibleHTMLTag":"AUTO","isDecorativeImage":false,"ariaAttributes":{},"interactions":[],"paddingTop":235.0,"paddingBottom":235.0,"layoutMode":"VERTICAL","itemSpacing":900.0,"counterAxisAlignItems":"CENTER","counterAxisSizingMode":"FIXED","children":["I15:1343;74:614","I15:1343;74:675","I15:1343;74:677","I15:1343;93:177","I15:1343;99:192","I15:1343;74:747","I15:1343;74:744"],"componentProperties":{},"overrides":[]},"50:2684":{"type":"RECTANGLE","id":"50:2684","name":"Rectangle 2","overrideKey":"99:317","absoluteBoundingBox":{"x":2553.235595703125,"y":7237.5029296875,"width":910.6115112304688,"height":629.21337890625},"isolatedAbsoluteRenderBounds":{"x":2553.235595703125,"y":7237.5029296875,"width":910.611572265625,"height":629.21337890625},"relativeTransform":[[1.0,0.0,13.235595703125],[0.0,1.0,19.500587463378906]],"size":{"x":910.6115112304688,"y":629.21337890625},"fills":[{"blendMode":"NORMAL","type":"SOLID","color":{"r":1.0,"g":0.8274509906768799,"b":0.8313725590705872,"a":1.0},"visible":true,"opacity":1.0}],"constraints":{"vertical":"SCALE","horizontal":"SCALE"},"constraintValues":{"left":{"pixelOffset":5.684341886080802e-14,"sizeFraction":0.2892083428926777},"right":{"pixelOffset":0.0,"sizeFraction":0.9929266668729473},"top":{"pixelOffset":0.0,"sizeFraction":0.46828310291243447},"bottom":{"pixelOffset":0.0,"sizeFraction":0.8974873177188806}},"strokeAlign":"INSIDE","strokes":[],"effects":[],"accessibleHTMLTag":"AUTO","isDecorativeImage":false,"ariaAttributes":{},"interactions":[]}},"assetIdToGuid":{"VariableCollectionId:7c5f5a79620c1c68e6e553b7b51078dd6262a5d7/18:0":"1:2","VariableID:8033d4f0114a6e3fe444b55321be870ebb679842/18:2":"1:3"},"guidToUrl":{"46:649":"/slide-9-abrupt","46:476":"/slide-9","19:500":"/slide-8","15:1232":"/slide-5","17:1604":"/slide-7","16:1410":"/slide-6","13:955":"/slide-4","1:83":"/","9:422":"/slide-3","5:38":"/slide-2"},"fonts":{"Inconsolata:Bold":{"id":"Inconsolata_wdth_wght__1","url":"/_woff/v2/Inconsolata_wdth_wght__1/Inconsolata_wdth_wght__1.woff2","source":1,"italic":false,"weight":700,"variationAxes":[{"tag":"wght","value":700.0,"name":"Weight"},{"tag":"wdth","value":100.0,"name":"Width"}],"subsets":{"baseUrl":"/_woff/v2/Inconsolata_wdth_wght__1/","subsetMappings":[{"unicodeRange":"U+0000-00A0,U+00A2-00A9,U+00AC-00AE,U+00B0-00B7,U+00B9-00BA,U+00BC-00BE,U+00D7,U+00F7,U+2000-206F,U+2074,U+20AC,U+2122,U+2190-21BB,U+2212,U+2215,U+F8FF,U+FEFF,U+FFFD","file":"Inconsolata_wdth_wght__1-english.woff2"},{"unicodeRange":"U+00A1,U+00AA-00AB,U+00AF,U+00B8,U+00BB,U+00BF-00D6,U+00D8-00F6,U+00F8-00FF,U+0131,U+0152-0153,U+02B0-02FF","file":"Inconsolata_wdth_wght__1-rest-latin.woff2"},{"unicodeRange":"U+0100-0130,U+0132-0151,U+0154-017F","file":"Inconsolata_wdth_wght__1-latin-extended-a.woff2"},{"unicodeRange":"U+0180-024F","file":"Inconsolata_wdth_wght__1-latin-extended-b.woff2"},{"unicodeRange":"U+1E00-1EFF","file":"Inconsolata_wdth_wght__1-latin-extended-additional.woff2"},{"unicodeRange":"U+0250-02AF,U+0300-1DFF,U+1F00-1FFF,U+2070-2073,U+2075-20AB,U+20AD-2121,U+2123-218F,U+21BC-2211,U+2213-2214,U+2216-F8FE,U+F900-FEFE,U+FF00-FFFC,U+FFFE-FFFF","file":"Inconsolata_wdth_wght__1-rest.woff2"}]}},"Noto Sans:Regular":{"id":"NotoSans-VF_2","url":"/_woff/v2/NotoSans-VF_2/NotoSans-VF_2.woff2","source":1,"italic":false,"weight":400,"variationAxes":[{"tag":"wght","value":400.0,"name":"Weight"},{"tag":"wdth","value":100.0,"name":"Width"},{"tag":"CTGR","value":0.0,"name":"CTGR"}],"subsets":{"baseUrl":"/_woff/v2/NotoSans-VF_2/","subsetMappings":[{"unicodeRange":"U+0000-00A0,U+00A2-00A9,U+00AC-00AE,U+00B0-00B7,U+00B9-00BA,U+00BC-00BE,U+00D7,U+00F7,U+2000-206F,U+2074,U+20AC,U+2122,U+2190-21BB,U+2212,U+2215,U+F8FF,U+FEFF,U+FFFD","file":"NotoSans-VF_2-english.woff2"},{"unicodeRange":"U+00A1,U+00AA-00AB,U+00AF,U+00B8,U+00BB,U+00BF-00D6,U+00D8-00F6,U+00F8-00FF,U+0131,U+0152-0153,U+02B0-02FF","file":"NotoSans-VF_2-rest-latin.woff2"},{"unicodeRange":"U+0100-0130,U+0132-0151,U+0154-017F","file":"NotoSans-VF_2-latin-extended-a.woff2"},{"unicodeRange":"U+0180-024F","file":"NotoSans-VF_2-latin-extended-b.woff2"},{"unicodeRange":"U+1E00-1EFF","file":"NotoSans-VF_2-latin-extended-additional.woff2"},{"unicodeRange":"U+0250-02AF,U+0300-1DFF,U+1F00-1FFF,U+2070-2073,U+2075-20AB,U+20AD-2121,U+2123-218F,U+21BC-2211,U+2213-2214,U+2216-F8FE,U+F900-FEFE,U+FF00-FFFC,U+FFFE-FFFF","file":"NotoSans-VF_2-rest.woff2"}]}},"Inconsolata:Regular":{"id":"Inconsolata_wdth_wght__1","url":"/_woff/v2/Inconsolata_wdth_wght__1/Inconsolata_wdth_wght__1.woff2","source":1,"italic":false,"weight":400,"variationAxes":[{"tag":"wght","value":400.0,"name":"Weight"},{"tag":"wdth","value":100.0,"name":"Width"}],"subsets":{"baseUrl":"/_woff/v2/Inconsolata_wdth_wght__1/","subsetMappings":[{"unicodeRange":"U+0000-00A0,U+00A2-00A9,U+00AC-00AE,U+00B0-00B7,U+00B9-00BA,U+00BC-00BE,U+00D7,U+00F7,U+2000-206F,U+2074,U+20AC,U+2122,U+2190-21BB,U+2212,U+2215,U+F8FF,U+FEFF,U+FFFD","file":"Inconsolata_wdth_wght__1-english.woff2"},{"unicodeRange":"U+00A1,U+00AA-00AB,U+00AF,U+00B8,U+00BB,U+00BF-00D6,U+00D8-00F6,U+00F8-00FF,U+0131,U+0152-0153,U+02B0-02FF","file":"Inconsolata_wdth_wght__1-rest-latin.woff2"},{"unicodeRange":"U+0100-0130,U+0132-0151,U+0154-017F","file":"Inconsolata_wdth_wght__1-latin-extended-a.woff2"},{"unicodeRange":"U+0180-024F","file":"Inconsolata_wdth_wght__1-latin-extended-b.woff2"},{"unicodeRange":"U+1E00-1EFF","file":"Inconsolata_wdth_wght__1-latin-extended-additional.woff2"},{"unicodeRange":"U+0250-02AF,U+0300-1DFF,U+1F00-1FFF,U+2070-2073,U+2075-20AB,U+20AD-2121,U+2123-218F,U+21BC-2211,U+2213-2214,U+2216-F8FE,U+F900-FEFE,U+FF00-FFFC,U+FFFE-FFFF","file":"Inconsolata_wdth_wght__1-rest.woff2"}]}},"Inclusive Sans:Regular":{"id":"InclusiveSans-Regular_1","url":"/_woff/v2/InclusiveSans-Regular_1/InclusiveSans-Regular_1.woff2","source":1,"italic":false,"weight":400,"subsets":{"baseUrl":"/_woff/v2/InclusiveSans-Regular_1/","subsetMappings":[{"unicodeRange":"U+0000-00A0,U+00A2-00A9,U+00AC-00AE,U+00B0-00B7,U+00B9-00BA,U+00BC-00BE,U+00D7,U+00F7,U+2000-206F,U+2074,U+20AC,U+2122,U+2190-21BB,U+2212,U+2215,U+F8FF,U+FEFF,U+FFFD","file":"InclusiveSans-Regular_1-english.woff2"},{"unicodeRange":"U+00A1,U+00AA-00AB,U+00AF,U+00B8,U+00BB,U+00BF-00D6,U+00D8-00F6,U+00F8-00FF,U+0131,U+0152-0153,U+02B0-02FF","file":"InclusiveSans-Regular_1-rest-latin.woff2"},{"unicodeRange":"U+0100-0130,U+0132-0151,U+0154-017F","file":"InclusiveSans-Regular_1-latin-extended-a.woff2"},{"unicodeRange":"U+0180-024F","file":"InclusiveSans-Regular_1-latin-extended-b.woff2"},{"unicodeRange":"U+1E00-1EFF","file":"InclusiveSans-Regular_1-latin-extended-additional.woff2"},{"unicodeRange":"U+0250-02AF,U+0300-1DFF,U+1F00-1FFF,U+2070-2073,U+2075-20AB,U+20AD-2121,U+2123-218F,U+21BC-2211,U+2213-2214,U+2216-F8FE,U+F900-FEFE,U+FF00-FFFC,U+FFFE-FFFF","file":"InclusiveSans-Regular_1-rest.woff2"}]}},"VT323:Regular":{"id":"VT323-Regular_1","url":"/_woff/v2/VT323-Regular_1/VT323-Regular_1.woff2","source":1,"italic":false,"weight":400,"subsets":{"baseUrl":"/_woff/v2/VT323-Regular_1/","subsetMappings":[{"unicodeRange":"U+0000-00A0,U+00A2-00A9,U+00AC-00AE,U+00B0-00B7,U+00B9-00BA,U+00BC-00BE,U+00D7,U+00F7,U+2000-206F,U+2074,U+20AC,U+2122,U+2190-21BB,U+2212,U+2215,U+F8FF,U+FEFF,U+FFFD","file":"VT323-Regular_1-english.woff2"},{"unicodeRange":"U+00A1,U+00AA-00AB,U+00AF,U+00B8,U+00BB,U+00BF-00D6,U+00D8-00F6,U+00F8-00FF,U+0131,U+0152-0153,U+02B0-02FF","file":"VT323-Regular_1-rest-latin.woff2"},{"unicodeRange":"U+0100-0130,U+0132-0151,U+0154-017F","file":"VT323-Regular_1-latin-extended-a.woff2"},{"unicodeRange":"U+0180-024F","file":"VT323-Regular_1-latin-extended-b.woff2"},{"unicodeRange":"U+1E00-1EFF","file":"VT323-Regular_1-latin-extended-additional.woff2"},{"unicodeRange":"U+0250-02AF,U+0300-1DFF,U+1F00-1FFF,U+2070-2073,U+2075-20AB,U+20AD-2121,U+2123-218F,U+21BC-2211,U+2213-2214,U+2216-F8FE,U+F900-FEFE,U+FF00-FFFC,U+FFFE-FFFF","file":"VT323-Regular_1-rest.woff2"}]}}},"assets":{"f988913985c9e710495e2cdf2e4b29bccf1ce074":{"type":"GENERATED_ASSET","url":"f988913985c9e710495e2cdf2e4b29bccf1ce074.svg","size":{"x":548.3937377929688,"y":221.5504150390625},"offsets":{"left":{"value":-0.9289360830298349,"unit":"PERCENT"},"right":{"value":-0.9286831361490767,"unit":"PERCENT"},"top":{"value":-2.363691271754975,"unit":"PERCENT"},"bottom":{"value":-2.3640546210456237,"unit":"PERCENT"}},"format":"SVG"},"6bff14706552884c26074230bef9e19f0fb53ca2":{"type":"GENERATED_ASSET","url":"6bff14706552884c26074230bef9e19f0fb53ca2.svg","size":{"x":311.0,"y":381.0},"offsets":{"left":{"value":0.0,"unit":"PERCENT"},"right":{"value":0.0,"unit":"PERCENT"},"top":{"value":0.0,"unit":"PERCENT"},"bottom":{"value":0.0,"unit":"PERCENT"}},"format":"SVG"},"3a6409c8883d64eae5e7cf47e9ccd0c9f2779068":{"type":"PAINT_ASSET","url":"3a6409c8883d64eae5e7cf47e9ccd0c9f2779068.png","size":{"x":1024.0,"y":776.0}},"5c3f1c9592c4ed696fc55c701828672253a60586":{"type":"GENERATED_ASSET","url":"5c3f1c9592c4ed696fc55c701828672253a60586.svg","size":{"x":167.0,"y":205.0},"offsets":{"left":{"value":0.0,"unit":"PERCENT"},"right":{"value":0.0,"unit":"PERCENT"},"top":{"value":0.0,"unit":"PERCENT"},"bottom":{"value":0.0,"unit":"PERCENT"}},"format":"SVG"},"ab920b0f26621e113e5411c1bbf88b324f20cc48":{"type":"PAINT_ASSET","url":"ab920b0f26621e113e5411c1bbf88b324f20cc48.png","size":{"x":858.0,"y":886.0}},"6517e6c698e55198654969624d21e305157b1413":{"type":"GENERATED_ASSET","url":"6517e6c698e55198654969624d21e305157b1413.svg","size":{"x":944.202514648443,"y":662.9973907470812},"offsets":{"left":{"value":-5.775453575436586e-13,"unit":"PERCENT"},"right":{"value":0.0,"unit":"PERCENT"},"top":{"value":-2.3014872366875796e-06,"unit":"PERCENT"},"bottom":{"value":0.0,"unit":"PERCENT"}},"format":"SVG"},"0a4d36731eb151843e5df7a85aaeb2600ffe5f36":{"type":"GENERATED_ASSET","url":"0a4d36731eb151843e5df7a85aaeb2600ffe5f36.svg","size":{"x":704.1138916021166,"y":507.2801513671875},"offsets":{"left":{"value":-7.870209596080279e-11,"unit":"PERCENT"},"right":{"value":0.0,"unit":"PERCENT"},"top":{"value":-3.861993586844518e-11,"unit":"PERCENT"},"bottom":{"value":-1.2031806781690532e-05,"unit":"PERCENT"}},"format":"SVG"},"6aeec36bd7b615a70ef49cfb80d0deb4d7741a3a":{"type":"PAINT_ASSET","url":"6aeec36bd7b615a70ef49cfb80d0deb4d7741a3a.png","size":{"x":2370.0,"y":1290.0}},"c50563e3e046bfa0b1fa6545757236cc447d9f3a":{"type":"GENERATED_ASSET","url":"c50563e3e046bfa0b1fa6545757236cc447d9f3a.svg","size":{"x":704.1134033208666,"y":507.2803344728522},"offsets":{"left":{"value":-7.87021505383149e-11,"unit":"PERCENT"},"right":{"value":0.0,"unit":"PERCENT"},"top":{"value":-3.861991728169021e-11,"unit":"PERCENT"},"bottom":{"value":0.0,"unit":"PERCENT"}},"format":"SVG"},"1a28191bd5e037e02ee2cf096fb0a7ebc269581a":{"type":"PAINT_ASSET","url":"1a28191bd5e037e02ee2cf096fb0a7ebc269581a.png","size":{"x":1200.0,"y":738.0}},"5cefdeee8f4764d2d1026aa3b3468460f2f8665e":{"type":"PAINT_ASSET","url":"5cefdeee8f4764d2d1026aa3b3468460f2f8665e.png","size":{"x":1336.0,"y":1126.0}},"00cb0963c8130f92de196bc72818213bc75a16f2":{"type":"PAINT_ASSET","url":"00cb0963c8130f92de196bc72818213bc75a16f2.png","size":{"x":1024.0,"y":645.0}},"06d4b42238051ba8c9e64e25ca42537644601449":{"type":"PAINT_ASSET","url":"06d4b42238051ba8c9e64e25ca42537644601449.png","size":{"x":1024.0,"y":831.0}},"720d23834212e74dfdb5e0abf45fb6a106861dfd":{"type":"PAINT_ASSET","url":"720d23834212e74dfdb5e0abf45fb6a106861dfd.png","size":{"x":1072.0,"y":1032.0}},"fdc67aafac07ebde7f933aece5dcbe07a53e38a6":{"type":"PAINT_ASSET","url":"fdc67aafac07ebde7f933aece5dcbe07a53e38a6.png","size":{"x":2020.0,"y":1076.0}},"c6b6bb61a406f48e2508764d0bf6f83d2297264a":{"type":"PAINT_ASSET","url":"c6b6bb61a406f48e2508764d0bf6f83d2297264a.png","size":{"x":778.0,"y":778.0}},"2357e923eb6d974b63f49518118fd7e232d69d90":{"type":"PAINT_ASSET","url":"2357e923eb6d974b63f49518118fd7e232d69d90.png","size":{"x":1024.0,"y":795.0}},"98597c0a5a579be0a09b2d425ff52185b699971f":{"type":"GENERATED_ASSET","url":"98597c0a5a579be0a09b2d425ff52185b699971f.svg","size":{"x":944.202270507818,"y":662.99755859375},"offsets":{"left":{"value":-5.775455068784876e-13,"unit":"PERCENT"},"right":{"value":0.0,"unit":"PERCENT"},"top":{"value":0.0,"unit":"PERCENT"},"bottom":{"value":0.0,"unit":"PERCENT"}},"format":"SVG"},"ef2ddfc80b0b1b6ed8ad976d16042510832e806c":{"type":"PAINT_ASSET","url":"ef2ddfc80b0b1b6ed8ad976d16042510832e806c.png","size":{"x":3000.0,"y":1830.0}},"40161369bf6fe385afffb3f01db62d408e0698a2":{"type":"PAINT_ASSET","url":"40161369bf6fe385afffb3f01db62d408e0698a2.png","size":{"x":2048.0,"y":1117.0}},"e788d7b73a8a70c534a3c5cbc04bd076221ee7d2":{"type":"PAINT_ASSET","url":"e788d7b73a8a70c534a3c5cbc04bd076221ee7d2.png","size":{"x":1024.0,"y":947.0}},"d694aca7360065ca505577dabae57d725367d230":{"type":"PAINT_ASSET","url":"d694aca7360065ca505577dabae57d725367d230.png","size":{"x":1024.0,"y":842.0}}},"stablePathToAssetHash":{"50:2685":"98597c0a5a579be0a09b2d425ff52185b699971f","50:2676":"c50563e3e046bfa0b1fa6545757236cc447d9f3a","I15:1343;99:295":"0a4d36731eb151843e5df7a85aaeb2600ffe5f36","I15:1343;74:720":"6bff14706552884c26074230bef9e19f0fb53ca2","50:2705":"5c3f1c9592c4ed696fc55c701828672253a60586","I15:1343;99:364":"5c3f1c9592c4ed696fc55c701828672253a60586","I15:1343;74:743":"f988913985c9e710495e2cdf2e4b29bccf1ce074","50:2739":"f988913985c9e710495e2cdf2e4b29bccf1ce074","50:2723":"6bff14706552884c26074230bef9e19f0fb53ca2","I15:1343;99:318":"6517e6c698e55198654969624d21e305157b1413"},"animateRootIds":[],"siteSettings":{"scalingMode":"REFLOW","blockSearchIndexing":true,"labs":{"7E40910AE74B0A483FB7C572EAF579D247AA3603":false,"62582ACEEDA1BE3737221299D8B91E208025F1A3":false,"7464717929BF125D021BA2EC2CE3DD3FDA32FFCA":false,"03413F6F08EB5AE8BAC0FFAF722D852F02A991F4":true,"E5FBBA911B2B7A09E649D4BE6CDF8591EAEFC881":false},"title":"9/29 - BWW - Slide 5"},"sourceCodeHash":""}